{
  "company_type": "startup_saas",
  "label": "SaaSスタートアップ",
  "companies": [
    {
      "key": "tonari_hr",
      "name": "株式会社となり",
      "industry": "HR Tech",
      "size": "30",
      "company_profile": {
        "mission": "採用のミスマッチをなくす",
        "description": "人事経験者が創業したHR Techスタートアップ。社員の声を活かした採用プロセスの構築を支援するSaaSを開発。",
        "strengths": [
          "元人事のメンバーが多く、顧客の課題理解が深い",
          "フルリモート・フルフレックスで柔軟な働き方",
          "少数精鋭で一人ひとりの裁量が大きい"
        ],
        "tone": "カジュアルで親しみやすい。等身大のリアルさを大事にする。"
      },
      "tech_environment": {
        "tech_stack": "Ruby on Rails, React, TypeScript, AWS, PostgreSQL",
        "development_style": "1週間のスプリントによるスクラム開発を採用。ユーザーヒアリングに基づくアジャイルな改善サイクルを高速で回していて、エンジニアも仕様策定や企画の初期段階から参加するフラットな開発体制。"
      },
      "team_composition": [
        {
          "area": "management",
          "title": "ceo",
          "count": 1,
          "answers": {
            "q_founding_reason": [
              "前職の人事時代、どれだけ準備しても起きる『入社後のギャップ』に悩み、企業と候補者がもっと等身大で向き合える仕組みを作りたいと思い創業しました。"
            ],
            "q_company_vision": [
              "すべての人が、自分の居場所を納得して選べる社会。社名のように、隣に寄り添うような温かいテクノロジーで、採用を『選考』から『対話』に変えていきたいです。"
            ],
            "q_what_kind_of_people": [
              "自身の失敗や弱さもオープンに話せて、他人の課題を自分事として面白がれる、人間味のあるプロフェッショナルな方と一緒に歩みたいです。"
            ],
            "q_company_challenge": [
              "組織が30名を超え、文化を薄めずにどう広げていくか。また、SaaSとしての利便性と、人事という感情が動く領域のバランスをどう最適化するかが今の壁です。"
            ]
          }
        },
        {
          "area": "management",
          "title": "cto",
          "count": 1,
          "answers": {
            "q_company_vision": [
              "『技術で心理的障壁を下げる』ことです。複雑なデータをシンプルに見せ、人事が直感的に『この人が自社に合う』と確信を持てる、手触り感のあるプロダクトを追求します。"
            ],
            "q_what_kind_of_people": [
              "コードの美しさと同じくらい、画面の向こうにいる人事や候補者の笑顔にワクワクできるエンジニア。技術を手段として正しく使いこなせる方。"
            ],
            "q_company_challenge": [
              "ユーザー数急増に伴うパフォーマンス改善と、HRデータという機微な情報を扱うための堅牢なセキュリティ体制を、このスピード感を維持したまま構築することです。"
            ]
          }
        },
        {
          "area": "development",
          "title": null,
          "count": 10,
          "answers": {
            "q_why_joined": [
              "「1週間のスプリント」というリズムが、自分の短期集中型のスタイルに合っていると感じたからです。",
              "エンジニアが企画段階から口を出せると聞き、単なる作業員ではなく「プロダクトを作る一人」になれると思ったからです。",
              "面接で会ったメンバーがみんなフラットで、ここなら飾らずに自分を出せると直感しました。",
              "前職のHRサービスでの経験を活かしつつ、モダンなReact/TypeScript環境で開発したかったためです。",
              "「採用のミスマッチをなくす」という言葉が、自分自身の苦い転職経験に刺さりました。",
              "技術顧問の方が非常に優秀で、この環境ならRailsの深いところまで学べると確信しました。",
              "フルリモート・フルフレックスが徹底されており、育児と開発を無理なく両立できる点に惹かれました。",
              "ユーザーヒアリングにエンジニアも同席する文化があると聞き、ユーザーの声を直接聞きたかったからです。",
              "少数精鋭のチームで、一人でフロントからインフラまで広く触れるチャンスがあると感じました。",
              "社内のコミュニケーションがSlack中心で非常にオープンかつ親しみやすかったからです。"
            ],
            "q_what_attracted": [
              "週に一度のリリースで、自分の書いたコードがすぐに誰かの役に立つ実感が得られる点です。",
              "不要な書類作成がほとんどなく、コードを書くことと仕様を詰めることに時間を最大限割ける点です。",
              "「何が正しいか」を職種に関係なく言い合える、心理的安全性の高さです。",
              "新しい技術への好奇心が全社的に強く、ライブラリのアップデートなども積極的に行える点です。",
              "バグが出たときも「仕組み」で解決しようとする姿勢が徹底されている点です。",
              "開発PCや周辺機器への投資を惜しまない、エンジニアファーストな文化です。",
              "エンジニアもCSチームの商談録画を自由に見て、現場の温度感を知ることができる透明性です。",
              "ペアプログラミングやコードレビューが日常的に行われ、スキルアップが速い環境です。",
              "朝会が短く、あとは自分のリズムで集中して作業できる時間配分です。",
              "「それ、ユーザーは本当に嬉しいかな？」という問いが、常にエンジニアからも出るところです。"
            ],
            "q_team_atmosphere": [
              "雑談チャンネルが活発で、リモートでも孤独を感じない、温かくて賑やかなチームです。",
              "困ったときは「助けて」とすぐに言える雰囲気があり、みんなが手を止めてフォローしてくれます。",
              "定例ミーティングも笑いが絶えず、でも締めるところはしっかり締めるメリハリがあります。",
              "お互いのプライベートを尊重し合っていて、休みを取ることに誰も気を使わない文化です。",
              "誰かが書いた良いコードや修正を、全員で絵文字リアクションして褒め合う習慣があります。",
              "技術的な議論は熱いですが、相手への敬意を忘れない、大人のコミュニケーションです。",
              "「等身大」を大事にしているので、かっこつけずに分からないことを聞ける環境です。",
              "新しいメンバーへの歓迎ムードがすごくて、初日から馴染みやすいです。",
              "失敗を笑いに変えるのではなく、次の成功のための糧として真面目に面白がる雰囲気です。",
              "年齢やキャリアに関係なく、さん付けで呼び合うフラットでフラットな関係です。"
            ],
            "q_job_description": [
              "Ruby on Railsを用いた、採用管理SaaSの新規機能開発およびAPI設計。",
              "React/TypeScriptによる、人事担当者が使いやすい管理画面のUI改善。",
              "AWS（ECS/RDS）を利用した、スケーラブルなインフラ基盤の運用とコード化。",
              "ユーザーインタビューへの同席と、それに基づく機能要件の定義・ブラッシュアップ。",
              "PostgreSQLのクエリ最適化と、増大するデータに対するDBリファクタリング。",
              "CircleCIを用いたCI/CDパイプラインの整備と、テスト自動化の推進。",
              "デザインシステム構築への参加と、再利用性の高いコンポーネントの実装。",
              "モバイル対応を見据えたレスポンシブデザインの最適化とフロントエンド実装。",
              "社内向けデータ分析ツールの構築と、マーケチームへのデータ抽出支援。",
              "スクラムマスターとしてのスプリント運営と、開発プロセスの継続的改善。"
            ],
            "q_message_to_applicants": [
              "技術で人を幸せにしたい。そんなピュアな想いを持つ人と一緒に開発したいです。",
              "あなたのアイデアが、来週にはプロダクトの一部になります。このスピード感を楽しみましょう。",
              "「となり」にいて心地よい。そんなシステムを僕たちと一緒に作っていきませんか？",
              "HR領域はまだまだ課題だらけです。あなたの力で、採用をもっとハッピーに変えてください。",
              "技術力はもちろん、人間らしさを大事にするチームです。まずは気楽にお話ししましょう！",
              "フルリモートでも「繋がり」を感じられる、最高のチームがあなたを待っています。",
              "モダンな環境で、裁量を持って働きたいエンジニアにはぴったりの環境ですよ。",
              "仕事もプライベートも全力。そんな働き方を当たり前にできる組織です。",
              "コードを書くだけじゃ物足りない、プロダクトの未来を考えたいあなたへ。",
              "「自分らしく」働ける環境を、僕たちと一緒に育てていきましょう。"
            ]
          }
        },
        {
          "area": "sales",
          "title": null,
          "count": 5,
          "answers": {
            "q_why_joined": [
              "元人事が作ったプロダクトだからこそ、顧客の痛みに寄り添った提案ができると確信したからです。",
              "「売り込み」ではなく「相談に乗る」スタイルの営業を推奨している文化に惹かれました。",
              "自身の採用担当としての挫折経験を、このプロダクトを広めることで解消したいと思ったからです。",
              "少数精鋭で、営業戦略の立案から実行まで一気通貫で携われる裁量の大きさに惹かれました。",
              "プロダクトが本当に良いので、自信を持って「お隣さん」のような距離感で提案できると思ったからです。"
            ],
            "q_what_attracted": [
              "顧客からの要望が、翌週には「実装されました！」とエンジニアから報告が来るスピード感です。",
              "決まったトークスクリプトがなく、目の前のお客様にとって最適な提案を自分で考えられる自由度です。",
              "「受注して終わり」ではなく、導入後の活用まで全社でコミットする誠実な姿勢です。",
              "営業メンバー同士が商談のナレッジを惜しみなく共有し、チームで勝とうとする文化です。",
              "フルリモートながら、オンライン商談のノウハウが非常に蓄積されており、効率的に動ける点です。"
            ],
            "q_team_atmosphere": [
              "明るく前向きで、失敗しても「次はこうしよう」と笑い飛ばせるレジリエンスのあるチームです。",
              "Slackでの盛り上がりがすごくて、離れていても常に仲間を感じられる雰囲気です。",
              "お互いの成功を「自分のこと」のように喜べる、ピュアなメンバーが集まっています。",
              "上下関係がなく、若手の意見でも理にかなっていれば即採用されるフラットさがあります。",
              "「お客様の採用が成功すること」が唯一の正義、という共通認識があるため議論が建設的です。"
            ],
            "q_job_description": [
              "中堅・ベンチャー企業の経営層や人事部長への、採用課題のヒアリングと解決策の提案。",
              "潜在顧客に対するウェビナーの企画と、登壇を通じた「となり」のファン作り。",
              "フィールドセールスとしての商談実施から、クロージング、契約締結までのリード。",
              "インサイドセールスチームと連携した、ターゲット企業の選定とアプローチ手法の検討。",
              "プロダクトのフィードバック収集と、開発チームへの新機能アイディアの提案。"
            ],
            "q_message_to_applicants": [
              "「売る」こと以上に「助ける」ことに喜びを感じる営業の方、ぜひ仲間になってください。",
              "採用の常識を変えていく挑戦は、最高にエキサイティングです。一緒に市場を作りましょう。",
              "あなたの人間力が、そのままプロダクトの価値になる。そんな営業をしてみませんか？",
              "自律して、自由に、でも熱く働きたい。そんな欲張りなあなたを歓迎します。",
              "まずは私たちの「押し付けない営業」の秘密を、カジュアルに聞きに来てください。"
            ]
          }
        },
        {
          "area": "customer",
          "title": null,
          "count": 5,
          "answers": {
            "q_why_joined": [
              "「採用のミスマッチをなくす」というゴールに、最も長く関われるのがCSだと思ったからです。",
              "単なる操作サポートではなく、顧客の採用成功まで踏み込む姿勢に共感しました。",
              "前職のカスタマーサポートで感じていた「現場の声を開発に届けられない」もどかしさが、ここでは無さそうだったからです。",
              "となり社の「カジュアルで親しみやすい」というトーンが、自分の接客スタイルに合っていると感じたからです。",
              "人事経験を活かして、顧客企業の採用担当者と同じ目線で悩みを共有したいと考えたためです。"
            ],
            "q_what_attracted": [
              "CSチームの意見でUIがガラッと改善されるなど、プロダクトへの影響力が非常に強い点です。",
              "お客様から「となりさんのおかげで良い人が採れた」と手紙やメッセージを頂ける文化です。",
              "データの活用が進んでおり、どの顧客が困っているかが可視化されているため、先回りした支援ができる点です。",
              "CS向けのツール導入に積極的で、煩雑な事務作業が徹底的に自動化されている点です。",
              "「正解がない」採用という領域に対して、顧客と一緒に仮説検証を楽しめる雰囲気です。"
            ],
            "q_team_atmosphere": [
              "ホスピタリティの塊のようなメンバーばかりで、お互いの悩み相談も絶えない優しいチームです。",
              "難しい問い合わせが来ても、全員で知恵を出し合って解決する「抱え込まない」文化です。",
              "週に一度のランチ会（オンライン）など、業務以外の繋がりも大事にする温かい雰囲気です。",
              "ミスを責めるのではなく、カバーし合うのが当たり前という安心感があります。",
              "全員がプロダクトのファンで、どうすればもっと愛されるかを常に話し合っています。"
            ],
            "q_job_description": [
              "新規導入企業へのオンボーディングと、採用目標達成に向けたロードマップ作成。",
              "顧客向けのナレッジベース（ヘルプセンター）の構築と、分かりやすい解説記事の作成。",
              "定期的なヘルスチェックを通じた、活用度の低い顧客へのリバイバル施策の実行。",
              "ユーザーコミュニティの企画・運営を通じた、人事担当者同士の横の繋がりの創出。",
              "サポート窓口への問い合わせ対応と、そこから抽出した課題の開発チームへの共有。"
            ],
            "q_message_to_applicants": [
              "顧客の「一番近い相談相手」として、一緒に最高のカスタマーサクセスを作りませんか？",
              "あなたの優しさと専門知識が、誰かのキャリアを救うきっかけになります。",
              "未完成な部分も多いですが、その分CS組織を自分たちで創っていく楽しさがありますよ。",
              "「人」が好きな方には、これ以上ないほどやりがいを感じられる職場です。",
              "等身大のあなたで、お客様と向き合ってください。私たちが全力でバックアップします！"
            ]
          }
        },
        {
          "area": "corporate",
          "title": null,
          "count": 4,
          "answers": {
            "q_why_joined": [
              "自社がHR Tech企業だからこそ、世界一幸せな組織体現を支えたいと思ったからです。",
              "「となり」という温かい名前に込められた想いを、制度や福利厚生でも表現したかったからです。",
              "急成長中のフェーズで、人事・労務の基盤をゼロから整えていく経験に挑戦したかったためです。",
              "代表の「社員は家族であり、隣人である」という言葉に深く共感し、その環境を守りたいと思ったからです。"
            ],
            "q_what_attracted": [
              "「管理するためのルール」ではなく「自由を促進するためのルール」を作ろうとする姿勢です。",
              "コーポレートの業務にもエンジニアが興味を持ってくれ、自動化の相談に乗ってくれる協力体制です。",
              "情報の透明性が高く、経営会議の内容も全社員がリアルタイムで知ることができる風通しの良さです。",
              "各自が自律して働いているため、マイクロマネジメントが一切なく、信頼ベースで仕事が進む点です。"
            ],
            "q_team_atmosphere": [
              "落ち着いていて誠実、でも内面には「会社を良くしたい」という熱い想いがあるチームです。",
              "どんな些細なことでも「ありがとう」と言い合える、感謝の文化が根付いています。",
              "変化を恐れず、新しいツールや働き方を自らが実験台となって試していく柔軟さがあります。",
              "オンオフの切り替えが上手で、プライベートの充実を心から応援し合う雰囲気です。"
            ],
            "q_job_description": [
              "フルリモート・フルフレックス制度の運用・改善と、新しい働き方の制度設計。",
              "となり社のカルチャーを体現する採用広報活動と、等身大な採用プロセスの運営。",
              "月次決算・資金管理と、成長を加速させるための予算策定・進捗管理支援。",
              "社内イベントの企画・運営を通じた、リモート下でのコミュニケーション活性化。"
            ],
            "q_message_to_applicants": [
              "「となり」の縁の下の力持ちとして、一緒にワクワクする組織を作りませんか？",
              "決まった型はありません。あなたの理想とする「いい会社」をここで形にしてください。",
              "専門性を活かしつつ、職種の枠を超えて会社を盛り上げたい方を待っています。",
              "誠実で温かいメンバーと共に、スタートアップの基盤を創る濃密な時間を過ごしましょう。"
            ]
          }
        },
        {
          "area": "marketing",
          "title": null,
          "count": 2,
          "answers": {
            "q_why_joined": [
              "「となり」のブランドが持つ、飾らない等身大の魅力を世の中に広めたいと思ったからです。",
              "データと感情のどちらも大事にする、人間味のあるマーケティングができる環境だと感じたからです。"
            ],
            "q_what_attracted": [
              "広告の数字だけでなく、それによって「どんな出会いが生まれたか」という本質を重視する点です。",
              "現場のストーリーをコンテンツ化するための、社員全員の協力的な姿勢とオープンな社風です。"
            ],
            "q_team_atmosphere": [
              "クリエイティブな発想を尊重し合い、小さなアイディアも面白がって広げていくチームです。",
              "他部署との連携が非常にスムーズで、マーケの施策がすぐに全社に伝播する一体感があります。"
            ],
            "q_job_description": [
              "自社メディアを通じたHRトレンドの発信と、人事担当者向けのお役立ちコンテンツの制作。",
              "SNS運用を通じた「となり」のファン作りと、ユーザーコミュニティとの接点創出。"
            ],
            "q_message_to_applicants": [
              "単なる数字の獲得ではなく、価値ある『繋がり』をデザインしたいマーケターの方、ぜひ！",
              "あなたの言葉で、採用の未来を優しく、明るく変えていきましょう。"
            ]
          }
        },
        {
          "area": "design",
          "title": null,
          "count": 2,
          "answers": {
            "q_why_joined": [
              "人事という複雑な情報を扱うツールこそ、デザインの力で優しく解きほぐしたいと思ったからです。",
              "プロダクトのトーンである「親しみやすさ」を、UI/UXとして最高レベルで表現したかったからです。"
            ],
            "q_what_attracted": [
              "エンジニアと密に連携し、コンポーネント一つひとつの触り心地まで徹底的にこだわることができる環境です。",
              "ユーザーインタビューの結果がデザインに即反映され、改善のサイクルが目に見える速さで回る点です。"
            ],
            "q_team_atmosphere": [
              "言語化できない「違和感」も大切にし、納得いくまで対話を重ねる、丁寧でフラットなチームです。",
              "お互いのデザイン案に率直にフィードバックし合い、常にブラッシュアップを目指すストイックさがあります。"
            ],
            "q_job_description": [
              "SaaSのメイン画面および管理画面のUI/UXデザインと、プロトタイプの制作。",
              "ブランドガイドラインの策定と、それに基づくマーケティング資材やロゴ等のクリエイティブ管理。"
            ],
            "q_message_to_applicants": [
              "「使う人が優しい気持ちになれるデザイン」を、私たちと一緒に追求しませんか？",
              "プロダクトの成長をデザインの力で牽引したい、情熱あるデザイナーをお待ちしています。"
            ]
          }
        }
      ],
      "answers": {}
    },
    {
      "key": "kanari_fintech",
      "name": "株式会社Kanari",
      "industry": "FinTech",
      "size": "50",
      "company_profile": {
        "mission": "金融のアクセスを民主化し、挑戦を支えるインフラを創る",
        "description": "金融のプロフェッショナルとトップエンジニアが集結したFinTechスタートアップ。複雑な規制や古い慣習をテクノロジーで解き、中小企業の資金繰りを支える次世代金融プラットフォームを展開。",
        "strengths": [
          "金融ドメインの深い専門知識と、モダンな技術スタックを融合させる高い実装力",
          "業界最高水準の給与体系と、成果に対して率直にフィードバックし合う実力主義",
          "大手金融機関との強固なパートナーシップによる、スタートアップらしからぬ事業信頼性"
        ],
        "tone": "プロフェッショナルで誠実。信頼感をベースにしつつ、知的な挑戦意欲が滲むトーン。"
      },
      "team_composition": [
        {
          "area": "management",
          "title": "ceo",
          "count": 1,
          "answers": {
            "q_founding_reason": [
              "既存の金融システムでは救いきれない中小企業の情熱を、テクノロジーの力で正当に評価し、挑戦を後押ししたいと考え創業しました。"
            ],
            "q_company_vision": [
              "すべての事業者が、属性や規模に関わらず、必要な時に必要な資金にアクセスできる世界。日本の成長を支える新しい金融のスタンダードを目指しています。"
            ],
            "q_what_kind_of_people": [
              "高い誠実さを持ちつつ、既存の枠組みを疑い、自ら最適解を導き出せるプロフェッショナルな方と一緒に働きたいです。"
            ],
            "q_company_challenge": [
              "事業の急成長に伴い、金融機関としての堅牢なガバナンス構築と、スタートアップらしい開発スピードの両立が最大の挑戦です。"
            ]
          }
        },
        {
          "area": "management",
          "title": "cto",
          "count": 1,
          "answers": {
            "q_company_vision": [
              "「堅牢性と柔軟性の究極の融合」です。金融というミッションクリティカルな領域で、最高水準の技術を用いて、ユーザー体験を損なわない開発組織を創り上げます。"
            ],
            "q_what_kind_of_people": [
              "技術に対する純粋な探求心を持ち、同時に「そのコードがビジネスにどう貢献するか」を冷静に判断できるエンジニアを求めています。"
            ],
            "q_company_challenge": [
              "膨大な金融トランザクションを支えるスケーラブルなアーキテクチャへの刷新と、業界最高レベルのセキュリティ水準の維持です。"
            ]
          }
        },
        {
          "area": "management",
          "title": "coo",
          "count": 1,
          "answers": {
            "q_company_vision": [
              "Kanariのプラットフォームが、中小企業の経営において「なくてはならない空気のようなインフラ」として機能している状態を目指します。"
            ],
            "q_what_kind_of_people": [
              "複雑なオペレーションを構造化し、泥臭い改善を積み重ねながらも、常に全体最適を考えられる実行力の高い方です。"
            ],
            "q_company_challenge": [
              "提携先となる金融機関との連携をさらに深化させ、マーケットへの供給量を爆発的に拡大させるための組織体制の強化です。"
            ]
          }
        },
        {
          "area": "management",
          "title": "cfo",
          "count": 1,
          "answers": {
            "q_company_vision": [
              "透明性が高く、リスクが適切にコントロールされた健全な資本市場をテクノロジーで実現し、社会全体の資本効率を最大化させることです。"
            ],
            "q_what_kind_of_people": [
              "金融の常識を理解した上で、その常識をデジタルでどうアップデートできるかを共に考え、粘り強く交渉できる方です。"
            ],
            "q_company_challenge": [
              "多様化する資金調達手段の構築と、独自の与信アルゴリズムを裏付けるための精緻なデータガバナンスの確立です。"
            ]
          }
        },
        {
          "area": "development",
          "title": null,
          "count": 10,
          "answers": {
            "q_why_joined": [
              "金融ドメインの複雑なビジネスロジックをモダンな技術で解決することに、エンジニアとしての純粋な知的好奇心を刺激されました。",
              "最高水準のエンジニアが集まっていると聞き、この環境なら自分の技術力もさらに磨けると考えたからです。",
              "既存の不自由な金融体験を、自分たちのコードでスマートに変えられるという実感が持てたからです。",
              "技術顧問や経営陣との距離が近く、高度な技術選定がフラットに行われている点に惹かれました。",
              "「金融×テック」という、難易度は高いが社会的インパクトが非常に大きい領域に挑戦したかったためです。",
              "前職でのガチガチな開発体制に疑問を感じ、スピード感と技術的自由度の高いKanariを選びました。",
              "セキュリティとパフォーマンスの極致を求められる開発環境が、エンジニアとして最高の成長機会だと感じました。",
              "選考でのコードレビューが非常に鋭く、プロフェッショナルな集団であることを確信したからです。",
              "フルリモート・フルフレックスでありながら、アウトプットの質に対して非常にストイックな文化に共感しました。",
              "自身の書いたコードが、翌週には多くの中小企業の資金繰りを支えるという手触り感に魅力を感じました。"
            ],
            "q_what_attracted": [
              "一切の妥協を許さないコード品質へのこだわりと、それを支えるピアレビューの文化です。",
              "不要な会議が完全に排除されており、開発に集中できる時間が非常に多く確保されている点です。",
              "金融知識がない状態でも、ドメインエキスパートからいつでも直接学べるSlackのオープンな雰囲気です。",
              "新しいライブラリや技術スタックの導入判断が非常に速く、論理的であれば即採用されるスピード感です。",
              "給与体系が成果に基づき非常に高く設定されており、プロとして正当に評価されている実感があります。",
              "インフラからフロントまで、自分の意志次第でフルスタックに挑戦できる裁量の大きさです。",
              "データの信頼性が全ての基盤であるという認識が全社に浸透しており、技術的負債の解消にも理解がある点です。",
              "障害に対するポストモーテムが徹底されており、犯人探しではなく仕組みで解決する姿勢です。",
              "大手金融機関との提携など、スタートアップとは思えない大規模なプロジェクトに携われる点です。",
              "エンジニアが企画の初期段階から参加し、技術的な観点で仕様をブラッシュアップできる体制です。"
            ],
            "q_team_atmosphere": [
              "プロフェッショナル同士が互いに敬意を払い、論理的な議論を突き詰めることができる環境です。",
              "Slack上での技術情報のシェアが極めて活発で、常に最新の知見に触れることができます。",
              "トラブル時ほど落ち着いて、冷静に原因究明と対策に動く、大人のスタートアップという雰囲気です。",
              "成果にコミットしていれば、働く場所や時間は完全に自由。自律したメンバーが集まっています。",
              "四半期に一度の全社ミーティングでは、数字がオープンに共有され、経営の透明性が非常に高いです。",
              "各自が「自分の領域」に閉じこもらず、お互いのコードや設計を積極的に助け合う文化があります。",
              "無駄な精神論はなく、データとファクトに基づいた意思決定が行われるため、ストレスがありません。",
              "ランチや雑談チャンネルでも知的な会話が多く、常に刺激を受けることができます。",
              "新しい働き方やツールの導入に積極的で、コーポレートチームも開発側の要望を柔軟に汲み取ってくれます。",
              "ジュニア・シニアの垣根がなく、純粋に「何が正しいか」で物事が決まるフラットな組織です。"
            ],
            "q_job_description": [
              "マイクロサービスアーキテクチャに基づく、バックエンドAPIの設計と高い並行性を備えた実装。",
              "金融機関とのAPI連携基盤の構築と、それに伴う高度なセキュリティ実装。",
              "React/TypeScriptを用いた、複雑な資金管理を直感的に行えるSPAのフロントエンド開発。",
              "Terraformを用いたAWSインフラのコード化と、CI/CDパイプラインの最適化。",
              "独自の与信アルゴリズムをシステムへ落とし込むための、データモデリングと実装。",
              "大量の決済データをリアルタイムで処理するためのバッチ最適化とパフォーマンス改善。",
              "デザイナーと連携した、Atomic Designに基づくコンポーネントライブラリの開発とメンテナンス。",
              "決済システムにおける冪等性の担保や、トランザクション管理の徹底した設計・実装。",
              "社内のオペレーターが利用する管理画面のUX改善と、業務自動化ツールの開発。",
              "将来的なマルチテナント化を見据えた、データベース設計とスケーリング戦略の立案。"
            ],
            "q_message_to_applicants": [
              "金融の未来を自分の手で作りたいという、野心的なエンジニアをお待ちしています。",
              "技術力だけでなく、ビジネスを深く理解し、本質的な課題解決をしたい方には最高の環境です。",
              "「当たり前」を疑い、最高品質のシステムを共に創り上げましょう。",
              "あなたのキャリアにおいて、間違いなく最も濃密な開発経験を提供できると自負しています。",
              "技術の力で、挑戦する事業者の背中を支えるインフラを創りませんか？",
              "優秀な仲間と、難易度の高い課題に立ち向かう楽しさを、ぜひ味わってください。",
              "プロフェッショナルとして、自律して働きたい方にはこれ以上ないステージです。",
              "まずはカジュアルに、私たちの技術的なこだわりについてお話ししましょう。",
              "FinTechの可能性はまだ始まったばかりです。一緒にスタンダードを確立しましょう。",
              "あなたの書いた一行が、日本の経済を動かす力になります。参加をお待ちしています。"
            ]
          }
        },
        {
          "area": "operations",
          "title": null,
          "count": 10,
          "answers": {
            "q_why_joined": [
              "金融の専門性を活かしつつ、テクノロジーで業務を効率化していく過程に携わりたかったからです。",
              "伝統的な金融機関では叶わなかった、スピード感のある意思決定と改善サイクルを求めて入社しました。",
              "複雑な法規制の中で、いかにユーザーにスムーズな体験を提供できるかという課題に魅力を感じました。",
              "オペレーションが単なる作業ではなく、プロダクトの価値を最大化する戦略の一部であるという考えに共感しました。",
              "優秀なエンジニアと協力して、アナログな事務作業をゼロから自動化していく挑戦に惹かれました。",
              "「金融の民主化」という壮大なミッションを、現場の最前線から支えたいと思ったからです。",
              "実力主義の文化の中で、自分の成果がダイレクトに組織の成長に繋がる実感を得たかったためです。",
              "多様なバックグラウンドを持つメンバーと、新しい金融の形を模索することにワクワクしたからです。",
              "顧客に最も近い立場で、金融という不可欠なサービスを届ける責任感に惹かれました。",
              "これまでの経験を活かし、スタートアップの成長を土台から作り上げたいと考えたからです。"
            ],
            "q_what_attracted": [
              "現場の「不便」がすぐに開発チームへ共有され、システム改善として反映されるスピード感です。",
              "法務やコンプライアンスの専門家と密に連携しており、常に正しい知識をアップデートできる環境です。",
              "定型業務を徹底的に排除し、より高度で知的な判断に集中できる仕組みが整っている点です。",
              "自分の提案が、翌日には新しいオペレーションフローとして採用される柔軟な文化です。",
              "大手金融機関との大規模なプロジェクトを、現場の裁量で動かしていけるやりがいです。",
              "リモート環境でも、ドキュメント管理が徹底されており、情報の非対称性がない点に驚きました。",
              "「なぜこの作業が必要か」という問いに対し、常に本質的な目的を確認し合う合理的な文化です。",
              "多様なキャリアステップがあり、オペレーションから企画やプロダクト管理への道も開かれている点です。",
              "失敗を恐れず、より効率的な手法を試すことを推奨してくれるマネジメントの姿勢です。",
              "チーム全体の目標達成を重視し、お互いの負荷をフォローし合う協力的な体制です。"
            ],
            "q_team_atmosphere": [
              "プロフェッショナルとしての誠実さと、知的冒険心を兼ね備えたバランスの良いチームです。",
              "困ったときにはSlackですぐに誰かが助けてくれる、非常に心理的安全性の高い雰囲気です。",
              "定例ミーティングでも忖度のない意見交換が行われ、建設的な議論が常に生まれています。",
              "オンオフの切り替えが明確で、集中するときは集中し、休むときはしっかり休む社風です。",
              "新しいメンバーへのオンボーディングが丁寧で、異業界からの挑戦でも安心して馴染めます。",
              "互いの成果を賞賛し合う「Kudos」の文化が根付いており、モチベーションが高まります。",
              "管理されるのではなく、各自が目標に向かって自走することを期待される自律した組織です。",
              "論理的であることを重んじつつも、相手への配慮を忘れない優しいコミュニケーションが特徴です。",
              "各自が担当領域の専門家として、プロフェッショナルな自覚を持って業務に取り組んでいます。",
              "年齢や役職に関係なく、良いアイデアを出した人がリーダーシップを取れるフラットな関係です。"
            ],
            "q_job_description": [
              "プラットフォーム上の審査オペレーションの設計と、審査スピード向上のためのフロー改善。",
              "金融機関パートナーとの日次・月次の精算業務および、連携プロセスの最適化。",
              "法規制に基づいた本人確認（KYC）フローの構築と、最新のレギュレーション対応。",
              "顧客対応の品質管理と、FAQやヘルプセンターの整備による自己解決率の向上。",
              "開発チームと連携した、オペレーション自動化ツールの要件定義と導入支援。",
              "新規サービスリリースに伴う、事務マニュアルの策定とオペレーション体制の構築。",
              "トランザクションデータのモニタリングと、異常検知時のエスカレーション対応。",
              "サプライヤー（加盟店）への支払い管理および、入出金管理の正確性の担保。",
              "社内のDX推進の一環として、SaaSツールを組み合わせた業務フローの統合と最適化。",
              "顧客からのフィードバックを構造化し、プロダクト改善案として経営陣へ提案。"
            ],
            "q_message_to_applicants": [
              "金融の仕組みを中から変えていく、知的な楽しさを一緒に共有しましょう。",
              "プロフェッショナルとして、自らの手でオペレーションを「芸術」の域まで高めたい方を歓迎します。",
              "変化を楽しみ、常に「もっと良くできるはず」と問い続けられる方には最高の環境です。",
              "あなたの金融知識とテクノロジーを掛け合わせ、新しい価値を創り出しませんか？",
              "共に日本の挑戦者を支える、最強のインフラチームを作り上げましょう。",
              "主体的に動ける方には、無限のチャンスと裁量が用意されています。",
              "私たちは、単なる「事務」ではなく「金融のエンジニアリング」をしています。ぜひ力を貸してください。",
              "まずは私たちのビジョンを聞きに来てください。きっと共感いただけるはずです。",
              "Kanariの成長を支える心臓部を、一緒に進化させていきましょう。",
              "プロとしての誇りを持ち、誠実にお客様と向き合える仲間を待っています。"
            ]
          }
        },
        {
          "area": "sales",
          "title": null,
          "count": 8,
          "answers": {
            "q_why_joined": [
              "「金融の民主化」というミッションが、前職で感じていた中小企業の資金調達の課題と合致したからです。",
              "圧倒的に強いプロダクトがあり、自信を持って顧客に提案できる営業としての幸せを求めて入社しました。",
              "金融機関出身者が多く、ドメイン知識を深めながら、ITの力で変革を起こす過程に惹かれたためです。",
              "実力主義で、成果が正当に評価され、自身の市場価値を高められる環境だと感じたからです。",
              "大手銀行との提携など、スタートアップながら社会的な信頼基盤がある点に魅力を感じました。",
              "単なる「モノ売り」ではなく、顧客の経営課題を解決するコンサルティング営業を極めたかったためです。",
              "代表の金融改革に対する熱量と、具体的な戦略の整合性に感銘を受け、この船に乗りたいと思いました。",
              "業界最高水準の給与体系に加え、優秀なエンジニア陣とプロダクトを磨ける点に惹かれました。"
            ],
            "q_what_attracted": [
              "営業現場での要望が、驚くべきスピードで新機能として実装されるプロダクト開発との距離感です。",
              "インサイドセールスからフィールドセールスへの連携が精緻で、営業に集中できる仕組みが整っている点です。",
              "お客様から「これこそ求めていたサービスだ」と直接感謝される機会が非常に多いことです。",
              "セールスフォース等を駆使したデータドリブンな営業管理により、無駄な動きが一切ない点です。",
              "経営層と直接対話する機会が多く、金融や経済の仕組みに対する理解が日々深まっていく点です。",
              "競合優位性が明確で、論理的に説明すれば高い確率で納得いただけるプロダクトの完成度です。",
              "週次の勉強会で、最新の金融知識や他社の成功事例を惜しみなく共有し合う文化です。",
              "フルフレックスで、家族との時間や自己研鑽の時間を尊重しながら、高い成果を目指せる点です。"
            ],
            "q_team_atmosphere": [
              "個人で数字を追うだけでなく、チーム全体でナレッジを共有し高め合う、非常に意識の高い組織です。",
              "失敗してもその要因を徹底的に分析し、次に活かすことを称賛する建設的な文化です。",
              "Slackでの情報共有がとにかく速く、常に最新の市場状況を把握して商談に臨めます。",
              "ベテランの金融出身者と若手のIT出身者が融合し、互いに学び合っている心地よい緊張感があります。",
              "成果を出しているメンバーを素直に称え、その手法を全員で取り入れようとする貪欲さがあります。",
              "役職に関係なく、営業戦略の立案に誰でも参加できる、非常にオープンでフラットな環境です。",
              "プロフェッショナルとして自律しており、誰かに指示されるのを待つのではなく、自ら動くチームです。",
              "オンオフがはっきりしており、休暇を取る際もチームがフォローし合う安心感があります。"
            ],
            "q_job_description": [
              "中堅・中小企業の経営層に対し、資金繰り改善のためのファイナンスソリューションを提案。",
              "地域の金融機関との連携を強化し、共同で地域企業の成長を支援するアライアンス営業。",
              "インサイドセールスが獲得したリードに対し、WEB会議を中心とした効率的な商談とクロージング。",
              "展示会やウェビナーの企画から登壇まで、マーケティングチームと連携した新規リードの創出。",
              "顧客の要望をヒアリングし、プロダクトマネージャーにフィードバックして新機能を企画。",
              "既存顧客への定期的なフォローアップを通じた、継続利用の促進とアップセルの提案。",
              "営業資料のブラッシュアップやトークスクリプトの作成、CRMのデータ入力と分析。",
              "新人メンバーへの同行やロールプレイングを通じた、セールスチーム全体のレベル底上げ。"
            ],
            "q_message_to_applicants": [
              "金融のプロとして、顧客の挑戦を支える実感を味わいたい方はぜひ来てください。",
              "これまでの営業経験を、社会を変える大きなレバレッジとして活用してみませんか？",
              "自ら市場を切り拓く楽しさと、それに見合う最高の報酬・環境を用意しています。",
              "私たちは、本気で日本の金融インフラを作り変えようとしています。その最前線に立ちませんか？",
              "営業スキルを磨き、キャリアを一段階上のフェーズへ引き上げたい方を歓迎します。",
              "高い倫理観と情熱を持って、お客様の成功を共に喜び合える仲間を待っています。",
              "まずは私たちのプロダクトがどう社会を変えているか、お話しさせてください。",
              "挑戦を歓迎し、成果に誠実なチームで、最高の営業体験をしましょう。"
            ]
          }
        },
        {
          "area": "customer",
          "title": null,
          "count": 6,
          "answers": {
            "q_why_joined": [
              "導入がゴールではなく、お客様が資金調達を通じて成功するまで伴走したいと考えたからです。",
              "金融ドメインのCSとして、専門性を活かしながら顧客体験を追求できる環境に惹かれました。",
              "プロダクトの使い勝手が顧客の経営に直結するため、非常に責任ある役割だと感じたからです。",
              "ユーザーの声を直接開発に届け、サービスを共に育てる文化がKanariにはあったからです。",
              "前職でのカスタマーサポート経験を活かし、より戦略的な「カスタマーサクセス」を確立したかったためです。",
              "信頼が全ての金融ビジネスにおいて、CSこそがブランドの源泉であるという考えに共感しました。"
            ],
            "q_what_attracted": [
              "単なる操作説明に留まらず、顧客の財務分析にまで踏み込んだ提案ができるプロフェッショナルさです。",
              "チャーンレート（解約率）が極めて低く、プロダクトが本当に愛されていることを実感できる点です。",
              "お客様からのポジティブなフィードバックが、全社のSlackで常に共有され賞賛される文化です。",
              "CSチームの意見がプロダクトのロードマップに大きな影響を与える、ユーザー中心の組織体制です。",
              "ヘルススコアの分析など、データに基づいて科学的に顧客をサポートできる仕組みです。",
              "金融という難解な分野を、いかに分かりやすく、心地よく体験してもらうかというクリエイティビティです。"
            ],
            "q_team_atmosphere": [
              "お客様の成功を第一に考える、誠実で温かみのある、しかし仕事にはストイックなチームです。",
              "ナレッジ共有が非常に活発で、一つの成功事例が瞬時にチーム全体の標準になるスピード感です。",
              "職種間の壁がなく、技術的な疑問もエンジニアが即座に回答してくれる協力的な雰囲気です。",
              "「顧客のために」という共通言語があるため、議論が常に本質的で生産的です。",
              "お互いの担当顧客の状況を把握し、不在時でも完璧なフォローができる連携体制が整っています。",
              "自律したメンバーが多く、マイクロマネジメントのない、自由と責任が両立した環境です。"
            ],
            "q_job_description": [
              "新規導入企業へのオンボーディング実施と、スムーズな利用開始のための活用コンサルティング。",
              "顧客の利用状況データを分析し、活用度が低い顧客への先回りしたフォローアップ活動。",
              "ヘルプセンターのコンテンツ作成や、新機能リリース時のユーザー向けウェビナー企画。",
              "顧客からの機能要望の収集と、優先順位付け、および開発チームへのフィードバック。",
              "既存顧客の契約更新管理と、さらなる活用を促進するためのアップセル提案。",
              "ユーザーコミュニティの運営を通じて、顧客同士のナレッジ共有を促進する施策の実行。"
            ],
            "q_message_to_applicants": [
              "お客様の「ありがとう」をエネルギーに変えて、金融の未来を共に作りましょう。",
              "専門知識を武器に、顧客の経営を支えるパートナーとして成長したい方を歓迎します。",
              "CS組織をゼロから仕組み化し、スケールさせていくフェーズを一緒に楽しみませんか？",
              "私たちは、単なるサポートではなく、顧客の「挑戦」を成功に導く存在でありたいと考えています。",
              "あなたのコミュニケーション力と分析力で、Kanariのファンを増やしてください。",
              "プロフェッショナルな仲間と共に、最高水準の顧客体験を追求しましょう。"
            ]
          }
        },
        {
          "area": "corporate",
          "title": null,
          "count": 5,
          "answers": {
            "q_why_joined": [
              "急成長するFinTechスタートアップの基盤を、バックオフィスから強固に支えたいと思ったからです。",
              "金融機関としての高いガバナンスレベルと、スタートアップの柔軟性を両立させる挑戦に惹かれました。",
              "プロフェッショナルな社員たちが、余計なストレスなく成果に集中できる環境を創りたいと考えたためです。",
              "「金融の民主化」というミッションを、組織運営という側面から自分事として捉えたからです。",
              "自身の専門性（法務・人事・経理）を、より社会的意義の高いプロダクトのために活かしたいと思いました。"
            ],
            "q_what_attracted": [
              "コーポレート部門も「攻め」の姿勢で、DXを駆使して業務効率を極限まで高めている点です。",
              "フルリモート・フルフレックスといった多様な働き方を、自ら制度設計し運用できる裁量の大きさです。",
              "経営陣が組織文化の醸成を非常に重視しており、コーポレートの提案に耳を傾けてくれる点です。",
              "ISMSの取得や複雑な法的スキームの構築など、専門性の高いタスクに日々挑戦できる環境です。",
              "情報のオープンさが徹底されており、会社の現状を正確に把握した上で仕事ができる安心感です。"
            ],
            "q_team_atmosphere": [
              "細部までこだわり抜く正確さと、変化に即応する柔軟性を兼ね備えた、バランスの良いチームです。",
              "前例に縛られず、「今のKanariにとっての最適は何か」を常に考え抜く文化があります。",
              "困っている他部門のメンバーを放っておかない、高いホスピタリティを持ったメンバーが集まっています。",
              "役職に関係なく意見を出し合い、納得感を持って制度を決めていくプロセスが非常にクリアです。",
              "各自が自律して業務を完結させており、無駄な管理コストが発生しないプロの組織です。"
            ],
            "q_job_description": [
              "急拡大する組織に対応した採用戦略の立案・実行、および人事評価制度の運用・改善。",
              "金融規制への対応を含む契約書のドラフト作成・レビュー、およびコンプライアンス体制の構築。",
              "月次・年次決算業務に加え、予算管理や資金調達を支援する財務情報の整理。",
              "フルリモート環境を支えるITインフラの整備、およびISMS等のセキュリティ基準の運用管理。",
              "社員のエンゲージメントを高めるための社内イベント企画や、行動指針の浸透施策の実行。"
            ],
            "q_message_to_applicants": [
              "変化の激しい環境で、安定感と攻めの姿勢を両立できる仲間を探しています。",
              "社員全員が最高のパフォーマンスを出せる舞台を、私たちと共に創っていきませんか？",
              "専門スキルを活かして、スタートアップの成長を土台から牽引したい方を歓迎します。",
              "私たちはバックオフィスを「守り」ではなく「事業の加速装置」だと考えています。",
              "知的で誠実な仲間と一緒に、理想の組織を追求できることを楽しみにしています。"
            ]
          }
        },
        {
          "area": "data",
          "title": null,
          "count": 2,
          "answers": {
            "q_why_joined": [
              "金融という膨大かつ高精度なデータが集まるフィールドで、独自の与信モデルを構築したいと考えたからです。",
              "データ分析の結果が、そのまま企業の資金調達の可否という重要な意思決定に直結する責任感に惹かれました。"
            ],
            "q_what_attracted": [
              "経営陣がデータドリブンな意思決定を徹底しており、分析結果が即座に戦略に反映される点です。",
              "最新の機械学習手法や分析基盤（BigQuery等）を自由に活用でき、技術的な探求が推奨される環境です。"
            ],
            "q_team_atmosphere": [
              "論理的であることを最優先しつつ、データの裏側にあるユーザーの行動にも想像力を働かせるチームです。",
              "エンジニアやビジネスサイドと密に連携し、職種を超えてデータの活用方法を議論できるフラットな文化です。"
            ],
            "q_job_description": [
              "中小企業の財務データやトランザクションデータを活用した、動的な与信スコアリングモデルの設計・開発。",
              "不正利用を未然に防ぐための異常検知アルゴリズムの構築と、定常的な精度モニタリングおよび改善。"
            ],
            "q_message_to_applicants": [
              "データサイエンスの力で金融の常識を塗り替え、社会の資本効率を改善したい方を待っています。",
              "実データに基づいた仮説検証を高速で回し、プロダクトを科学的に進化させたい方には最高の舞台です。"
            ]
          }
        }
      ],
      "tech_environment": {
        "tech_stack": "Go, Next.js, TypeScript, AWS (EKS), MySQL, Terraform",
        "development_style": "金融水準のセキュリティと堅牢性を担保するため、マイクロサービスアーキテクチャを採用。ドメイン駆動設計(DDD)を意識し、厳格なコードレビューと自動化されたCI/CDパイプラインによる品質保証を徹底。"
      },
      "answers": {}
    },
    {
      "key": "bright_edu",
      "name": "株式会社Bright Path",
      "industry": "EdTech",
      "size": "25",
      "company_profile": {
        "mission": "一人ひとりの可能性を最大化する、学びのOSを届ける",
        "description": "元教師の代表が率いるEdTechスタートアップ。学校・塾・家庭をシームレスに繋ぎ、子供たちが主体的かつ最適に学べる環境をプロダクトの力で構築。",
        "strengths": [
          "現場（学校現場）への徹底的なリサーチに基づいた、ユーザー体験重視の開発スタイル",
          "『学び』を扱う組織として、社員の自己研鑽や挑戦を全力で称賛する心理的安全性の高さ",
          "社会的意義の大きさと、EdTech市場の成長性を両立させた持続可能なビジネスモデル"
        ],
        "tone": "温かみがあり情熱的。教育の未来を創るワクワク感を共有する、ポジティブなトーン。"
      },
      "tech_environment": {
        "tech_stack": "TypeScript, Next.js, Node.js, GCP, Firebase",
        "development_style": "教育現場のフィードバックを即座に反映するラピッドプロトタイピングを重視。生徒や教師にとってのアクセシビリティ・ユーザビリティを最優先とし、デザイナーとエンジニアが密に連携するペアプログラミングも積極的に導入。"
      },
      "team_composition": [
        {
          "area": "management",
          "title": "ceo",
          "count": 1,
          "answers": {
            "q_founding_reason": [
              "教師として教壇に立っていた際、子供たちの可能性がアナログな校務や情報の分断によって阻害されているのを目の当たりにし、テクノロジーで『学びのインフラ』を再定義したいと考え創業しました。"
            ],
            "q_company_vision": [
              "経済環境や地域格差に左右されず、すべての子供たちが自分に最適な学びを選択し、没頭できる『学びのOS』を世界中に届けることです。"
            ],
            "q_what_kind_of_people": [
              "教育という正解のない問いに対して、情熱を持って向き合い、ユーザーである生徒や先生の喜びを自分のこととして捉えられる方と働きたいです。"
            ],
            "q_company_challenge": [
              "プロダクトの導入校数が急増しており、安定したシステム基盤の強化と、教育現場の多様なニーズに応えるための組織規模の拡大が急務となっています。"
            ]
          }
        },
        {
          "area": "management",
          "title": "cto",
          "count": 1,
          "answers": {
            "q_company_vision": [
              "最新のテクノロジーを、教育現場の誰もが直感的に使える『優しい道具』として昇華させ、データに基づいた新しい教育体験をスタンダードにすることです。"
            ],
            "q_what_kind_of_people": [
              "技術そのものだけでなく、それが『誰の、どんな学びを加速させるか』にこだわり、泥臭い現場の課題解決を楽しめるエンジニアを求めています。"
            ],
            "q_company_challenge": [
              "膨大な学習ログを効果的に活用するためのデータ基盤の構築と、教育用プロダクトに求められる高い信頼性・アクセシビリティの追求を両立させることです。"
            ]
          }
        },
        {
          "area": "development",
          "title": null,
          "count": 10,
          "answers": {
            "q_why_joined": [
              "子供たちの未来を創る仕事に、得意のTypeScriptとNext.jsで挑戦できる点に魅力を感じました。",
              "元教師の代表の熱い想いに共感し、エンジニアリングで教育格差をなくしたいと思ったからです。",
              "Firebaseを用いたリアルタイム性の高い開発に興味があり、現場の反応が早い環境を求めて参加しました。",
              "教育現場のリサーチにエンジニアも同行し、直接ユーザーの声を聞けるスタイルに惹かれました。",
              "フルリモートで柔軟に働きながら、社会貢献度の高いプロダクト開発に携わりたかったためです。",
              "ペアプログラミングを積極的に導入しており、技術的な成長スピードが非常に早いと感じたからです。",
              "学びを大切にする文化があり、技術書購入支援などの自己研鑽を支える制度が充実していたためです。",
              "学校・塾・家庭を繋ぐという、壮大なプロダクトの構想にワクワクしたからです。",
              "モダンな技術スタックを使い、レガシーな教育業界をアップデートするやりがいを感じたからです。",
              "選考中に出会ったメンバー全員が、プロダクトとユーザーに対して真摯に向き合っていたからです。"
            ],
            "q_what_attracted": [
              "リリースした機能が翌日には学校現場で使われ、フィードバックが届くスピード感です。",
              "技術的な挑戦を歓迎する雰囲気があり、新しいライブラリの導入なども論理的であれば即採用されます。",
              "アクセシビリティへの意識が高く、誰もが使いやすいUIを追求する姿勢に誇りを持てます。",
              "デザイナーとの距離が非常に近く、Figmaを見ながらの仕様調整が日常的に行われる点です。",
              "コードレビューが丁寧かつ建設的で、チーム全体でコードの品質を高める文化が浸透しています。",
              "GCPやFirebaseの機能をフルに活用し、スケーラブルな構成を自ら設計できる点です。",
              "職種に関係なく、プロダクトの企画段階から意見を求められるフラットな環境です。",
              "教育のプロであるCSチームから、現場のリアルな困りごとをいつでも聞ける環境です。",
              "1週間スプリントが機能しており、常に目標が明確で無駄な会議が一切ないところです。",
              "エラーやトラブルが起きた際も個人を責めず、ポストモーテムを通じて仕組みを改善する文化です。"
            ],
            "q_team_atmosphere": [
              "「学び」を扱うチームらしく、新しい知識の共有やLT会が活発に行われる温かい雰囲気です。",
              "心理的安全性が高く、ジュニアからシニアまで率直に意見を出し合える環境です。",
              "Slackでのやり取りも丁寧で、リモートワークでも連携が取りやすい心地よさがあります。",
              "夕会での進捗共有だけでなく、雑談チャンネルで技術ネタや趣味の話も盛り上がります。",
              "各自が自律して動いており、マイクロマネジメントのない信頼に基づいたチームです。",
              "困ったときには誰かがすぐに「ハドル」で助けてくれる、協力体制が整っています。",
              "家庭や育児を大切にするメンバーが多く、ライフスタイルを尊重し合う雰囲気です。",
              "失敗を恐れず、まずはプロトタイプを作ってみようという前向きな姿勢に溢れています。",
              "プロダクトへの愛着が強く、より良い体験のために細部まで議論し尽くす熱量があります。",
              "お互いの強みを理解し、苦手な部分は補い合うプロフェッショナルな集団です。"
            ],
            "q_job_description": [
              "Next.jsを用いたフロントエンド開発を中心に、学習管理画面のUI/UX改善を担当しています。",
              "Node.jsとFirebaseでのバックエンド実装、およびリアルタイム通信の最適化を行っています。",
              "GCPを用いたインフラ構築と、CI/CDパイプラインの整備による開発効率の向上を担当しています。",
              "生徒向けの学習アプリ開発と、アクセシビリティ向上のためのコンポーネント設計をしています。",
              "教職員向け管理システムの要件定義からDB設計、API実装までエンドツーエンドで担当しています。",
              "大規模な学習データの分析基盤の構築と、パフォーマンスの最適化を担っています。",
              "新機能リリースのためのプロトタイピングと、現場でのユーザーテストへの同行・改善提案です。",
              "TypeScriptを用いた型安全なコードベースの維持と、リファクタリングの推進を担当しています。",
              "モバイル表示の最適化と、低速なネットワーク環境でも動作するオフライン対応の設計です。",
              "セキュリティ要件の策定と、ISMS準拠に向けたシステム面の整備をリードしています。"
            ],
            "q_message_to_applicants": [
              "教育の未来を自分たちの手で作りたい方、ぜひ一度カジュアルにお話ししましょう！",
              "あなたの技術が、明日の授業を変えるかもしれません。一緒にワクワクする開発をしませんか？",
              "技術への探究心と社会への貢献心、両方を満たせる最高の環境がここにあります。",
              "エンジニアリングの力で、子供たちの可能性を広げる挑戦に力を貸してください。",
              "フラットな組織で、自らプロダクトを育てていきたい方を心から歓迎します。",
              "教育業界のDXはまだ始まったばかりです。一緒にデファクトスタンダードを創りましょう。",
              "コードの先にいる子供たちの笑顔を想像しながら開発できる方、お待ちしています！",
              "学びを止めることのない、堅牢で優しいシステムを共に構築していきましょう。",
              "成長途中の組織だからこそ、技術選定から組織作りまで幅広く関われるチャンスがあります。",
              "「教育×IT」の領域で、世界一のユーザー体験を目指す仲間を探しています。"
            ]
          }
        },
        {
          "area": "design",
          "title": null,
          "count": 2,
          "answers": {
            "q_why_joined": [
              "子供から高齢の先生まで、誰一人取り残さないためのユニバーサルなデザインを教育に届けたかったからです。",
              "現場の一次情報に基づいたUXデザインを重視する文化に共感し、デザインの力で教育を変えたいと思いました。"
            ],
            "q_what_attracted": [
              "デザイナーも実際の授業を参観し、ユーザーの表情を見ながらデザインを磨き上げられる環境です。",
              "エンジニアとデザインシステムを共創しており、一貫性のあるプロダクト開発がスムーズに行える点です。"
            ],
            "q_team_atmosphere": [
              "意図や根拠を大切にする文化で、論理的かつクリエイティブな議論が尊重されるチームです。",
              "デザイナー同士のフィードバックが頻繁にあり、お互いの感性を刺激し合いながら成長できます。"
            ],
            "q_job_description": [
              "学習アプリのUIデザインから、生徒のモチベーションを高めるためのゲーミフィケーションの設計まで。",
              "デザインシステムの構築と、教育現場でのインタビューを通じたUXリサーチおよび改善提案。"
            ],
            "q_message_to_applicants": [
              "「使いやすい」の先にある「学びたくなる」デザインを、一緒に追求していきませんか？",
              "教育現場の複雑さを、シンプルで美しい体験に変える挑戦を楽しめるデザイナーを募集しています。"
            ]
          }
        },
        {
          "area": "planning",
          "title": null,
          "count": 3,
          "answers": {
            "q_why_joined": [
              "教育格差という社会課題に対し、持続可能なビジネスモデルで解決に挑む姿勢に惹かれたからです。",
              "プロダクトの成長が、そのまま子供たちの選択肢の増加に直結する点に大きなやりがいを感じました。",
              "中長期的な視点で、日本の教育のあり方そのものをアップデートする戦略を描きたいと思ったからです。"
            ],
            "q_what_attracted": [
              "代表の直下で、経営の意思決定プロセスを間近で見ながらスピード感を持って仕事ができる点です。",
              "データ分析に基づく合理的な判断と、現場の感情を大切にする文化が両立しているところです。",
              "行政や学校法人など、多様なステークホルダーを巻き込んだダイナミックな事業展開ができる環境です。"
            ],
            "q_team_atmosphere": [
              "常に「本質的な価値は何か」を問い直し、前例のないことにも臆せず挑戦する前向きな雰囲気です。",
              "数字には厳しいですが、その背景にあるユーザーのストーリーを大切にする誠実なチームです。",
              "各部門との連携が密で、全社が一丸となってミッションに向かう一体感があります。"
            ],
            "q_job_description": [
              "全社のKPI設計と各部門の数値管理、および達成のための施策立案と進捗フォローを担当しています。",
              "新規事業の市場調査、自治体向け導入モデルの策定、および提携パートナーの開拓を担っています。",
              "プロダクトのロードマップ策定に向けたユーザーデータの分析と、優先順位の意思決定サポートです。"
            ],
            "q_message_to_applicants": [
              "不確実な未来を、ロジックと情熱で切り拓いていくプロセスを一緒に楽しみましょう。",
              "教育市場のルールを書き換えるような、インパクトのある事業を共に作り上げましょう。",
              "あなたの戦略で、全国の教室の風景が変わります。その手応えを実感してみませんか？"
            ]
          }
        },
        {
          "area": "customer",
          "title": null,
          "count": 4,
          "answers": {
            "q_why_joined": [
              "学校現場の先生方が、プロダクトを最大限に活用して授業を楽しめるよう支えたいと思ったからです。",
              "導入して終わりではなく、活用を通じて生徒が変わっていく姿を一番近くで見守りたかったためです。",
              "元教師として、現場の苦労がわかるからこそ提供できる価値があると考え、CSの道を選びました。",
              "ユーザーの声を集約し、開発チームと共にプロダクトを磨き上げる架け橋になりたいと感じたからです。"
            ],
            "q_what_attracted": [
              "先生方から直接「授業がやりやすくなった」という感謝の言葉をいただける、何物にも代えがたいやりがいです。",
              "現場での活用事例が社内で即座に共有され、良いアイデアがすぐにプロダクトへ反映される文化です。",
              "単なる操作説明ではなく、教育の質を高めるためのコンサルティングに近い提案ができる点です。",
              "解約率が極めて低く、プロダクトが現場に深く愛されていることを実感できる環境です。"
            ],
            "q_team_atmosphere": [
              "ユーザー目線を徹底するプロフェッショナルさと、お互いを思いやる優しさが共存するチームです。",
              "成功事例だけでなく「なぜ上手くいかなかったか」をオープンに共有し、次に活かす学びの文化があります。",
              "現場の多忙さを理解し、どのように負担を減らせるかを真剣に議論できる誠実な雰囲気です。",
              "定期的なミーティングでノウハウを共有し合い、チーム全体のコンサルスキルを高めています。"
            ],
            "q_job_description": [
              "新規導入校へのオンボーディング支援と、活用推進のための研修会やワークショップの企画・運営。",
              "活用ログに基づいた定期的な振り返り面談（QBR）の実施と、活用プランの提案。",
              "ユーザー向けヘルプサイトの構築、および事例紹介記事の執筆を通じたナレッジシェア。",
              "先生方からのフィードバックの構造化と、開発チームへの優先順位を含めた改善要望の提案。"
            ],
            "q_message_to_applicants": [
              "先生や生徒の伴走者として、教育の現場を一番熱く盛り上げたい方をお待ちしています！",
              "あなたのコミュニケーションが、学校の未来を変える一歩になります。一緒に歩んでいきましょう。",
              "CS組織の立ち上げや仕組み化に興味がある方にとって、非常に刺激的なフェーズです。",
              "教育への想いを形にし、現場の課題を一つずつ解決していく喜びを分かち合いましょう。"
            ]
          }
        },
        {
          "area": "sales",
          "title": null,
          "count": 3,
          "answers": {
            "q_why_joined": [
              "EdTechという成長市場で、社会的意義とビジネスの成長を両立させたいと思ったからです。",
              "プロダクトが圧倒的に強く、自信を持ってお客様に「価値がある」と提案できる環境だったからです。",
              "アナログな教育現場にデジタルを届けることで、日本の教育の未来を変革したいという使命感からです。"
            ],
            "q_what_attracted": [
              "現場のリサーチ結果に基づいた「売れる理由」が明確で、提案の精度が非常に高い点です。",
              "受注して終わりではなく、CSチームと密に連携して顧客の成功を最後まで見届けられる仕組みです。",
              "営業のフィードバックが開発に即反映されるため、顧客ニーズに寄り添った柔軟な提案ができるところです。"
            ],
            "q_team_atmosphere": [
              "個人の目標達成はもちろん、チーム全体でノウハウを共有して高め合う文化が根付いています。",
              "失敗した商談も「次に活かすための財産」として捉え、改善策を全員で考える前向きなチームです。",
              "オンオフの切り替えがはっきりしており、集中して成果を出し、しっかり休むスタイルが定着しています。"
            ],
            "q_job_description": [
              "自治体や学校法人、大手塾チェーンへの導入提案から、契約締結までのリード獲得・商談を担当しています。",
              "共催ウェビナーの企画や教育系展示会への出展を通じて、新規顧客の接点創出をリードしています。",
              "既存のパートナー企業とのアライアンス構築や、エリアごとの販売戦略の立案・実行です。"
            ],
            "q_message_to_applicants": [
              "日本の教育をアップデートする先陣を切る営業として、共に市場を切り拓いていきましょう！",
              "「売る」だけではない、本質的な課題解決を提案したい営業の方には最高の環境です。",
              "あなたの熱意が、一校、一自治体の景色を変えていきます。このやりがいを一緒に味わいませんか？"
            ]
          }
        },
        {
          "area": "corporate",
          "title": null,
          "count": 1,
          "answers": {
            "q_why_joined": [
              "「学びのOSを届ける」という崇高なミッションを、組織の内側から支える基盤作りに挑戦したいと思ったからです。"
            ],
            "q_what_attracted": [
              "バックオフィスも「攻め」の姿勢で、フルリモート・フルフレックスを支えるためのDX推進に裁量を持って取り組める点です。"
            ],
            "q_team_atmosphere": [
              "少数精鋭で、全社員が最高のパフォーマンスを発揮できるよう細部まで配慮が行き届いた、誠実で柔軟なチームです。"
            ],
            "q_job_description": [
              "採用広報・労務・経理全般に加え、組織文化を醸成するための社内イベント企画や、ISMS取得に向けた環境整備を一手に担っています。"
            ],
            "q_message_to_applicants": [
              "変化の激しいスタートアップ期を楽しみながら、安定感のある組織の土台を共に作ってくれる仲間をお待ちしています。"
            ]
          }
        }
      ],
      "answers": {}
    },
    {
      "key": "vital_care",
      "name": "株式会社VitalCare",
      "industry": "HealthTech",
      "size": "40",
      "company_profile": {
        "mission": "健康を資産に変え、誰もが自分らしく生きられる社会を創る",
        "description": "医師とデータサイエンティストがタッグを組んだHealthTechスタートアップ。PHR（パーソナル・ヘルス・レコード）を活用し、予防医療を科学的根拠に基づいて社会実装するプラットフォームを展開。",
        "strengths": [
          "臨床的エビデンスを最優先する、誠実で妥協のないプロダクト開発のスタンス",
          "多職種（医師・管理栄養士・エンジニア）がフラットに連携する高度な専門家集団",
          "プライバシー保護とセキュリティに対して、業界最高水準の技術的投資を継続"
        ],
        "tone": "理知的で真摯。命や健康に向き合う重みを理解し、データの力を信じる落ち着いたトーン。"
      },
      "tech_environment": {
        "tech_stack": "Ruby on Rails, Vue.js, GraphQL, AWS, Docker",
        "development_style": "複雑な不動産業務フローを整理しながら開発するため、ビジネスサイド（営業・CS）とエンジニアが密に連携して仕様を策定。定期的にパフォーマンス改善や技術的負債の解消にスプリントを割くなど、長期的に愛されるプロダクト作りを重視しています。"
      },
      "team_composition": [
        {
          "area": "management",
          "title": "ceo",
          "count": 1,
          "answers": {
            "q_founding_reason": [
              "医師として臨床に携わる中で、病気になる前の『予防』の重要性を痛感し、テクノロジーの力で誰もが適切なケアを受けられる仕組みを作りたいと考え創業しました。"
            ],
            "q_company_vision": [
              "PHRが社会のインフラとなり、データに基づいて人々が自分の健康を正しくコントロールできる、病気に怯えない社会の実現を目指しています。"
            ],
            "q_what_kind_of_people": [
              "医療という尊い領域に対し、誠実に向き合える高い倫理観と、不確実な課題を論理的に解き明かす情熱を併せ持った方です。"
            ],
            "q_company_challenge": [
              "予防医療の価値を社会に定着させるためのビジネスモデルの深化と、急増するユーザーデータに対する強固なガバナンス体制の構築が今の壁です。"
            ]
          }
        },
        {
          "area": "management",
          "title": "cto",
          "count": 1,
          "answers": {
            "q_company_vision": [
              "最先端の技術を用いて、医療データの機密性と利活用を両立させ、世界で最も信頼されるHealthTechプラットフォームを築き上げることです。"
            ],
            "q_what_kind_of_people": [
              "技術を自己目的化せず、ユーザーの健康を守るという目的に対して、最適なアーキテクチャを追求できるプロダクト志向のエンジニアです。"
            ],
            "q_company_challenge": [
              "膨大なバイタルデータのリアルタイム処理の最適化と、グローバル展開を見据えたスケーラブルな開発組織への脱皮が急務です。"
            ]
          }
        },
        {
          "area": "management",
          "title": "cpo",
          "count": 1,
          "answers": {
            "q_company_vision": [
              "医療的な正しさと、日常に溶け込む心地よいUXを融合させ、ユーザーが自然と健康になっていく体験をデザインすることです。"
            ],
            "q_what_kind_of_people": [
              "多職種の専門的な知見を整理し、本質的なユーザー価値へと昇華させることができる、深い洞察力を持った方と働きたいです。"
            ],
            "q_company_challenge": [
              "専門的な医療ロジックを、いかに分かりやすくシンプルな体験としてプロダクトに落とし込めるか、その解像度を上げ続けることが課題です。"
            ]
          }
        },
        {
          "area": "data",
          "title": null,
          "count": 6,
          "answers": {
            "q_why_joined": [
              "PHRという膨大かつ価値のあるデータを、学術的・実務的に扱える環境に魅力を感じたためです。",
              "医師と協力して、データから新しい予防医療のエビデンスを作れる点に惹かれました。",
              "前職での分析スキルを、より直接的に人の命や健康に役立てたいと考えたからです。",
              "データサイエンティストが仕様策定の初期から関与できるフラットな体制だったからです。",
              "プライバシー保護技術への深い理解と投資を惜しまない姿勢に共感しました。",
              "研究とビジネスのバランスが良く、自分の知見を社会実装できると思ったからです。"
            ],
            "q_what_attracted": [
              "クリーニングの行き届いた質の高いバイタルデータに触れられる点です。",
              "仮説検証の結果が、プロダクトを通じてユーザーの行動変容に直結する点にやりがいを感じます。",
              "最新の論文をキャッチアップし、開発に反映させるアカデミックな文化が根付いています。",
              "ドメインエキスパートである医師に、Slackですぐに専門的な質問ができる環境です。",
              "データ活用に対する倫理規定が明確で、心理的に安心して分析に集中できる点です。",
              "統計モデルの実装において、精度だけでなく解釈性を重視する姿勢に納得感があります。"
            ],
            "q_team_atmosphere": [
              "常に論理的で冷静ですが、ユーザーの改善事例には全員で喜ぶ温かさがあります。",
              "バックグラウンドが多様で、異なる視点からのフィードバックが非常に刺激的です。",
              "週に一度のナレッジ共有会があり、技術的な議論が活発に行われています。",
              "お互いの専門性を尊重し合い、分からないことは率直に教え合う文化です。",
              "リモート環境でも非同期コミュニケーションが円滑で、孤独を感じません。",
              "数値に厳格でありながらも、その裏側にある『人間』への配慮を忘れないチームです。"
            ],
            "q_job_description": [
              "ユーザーの行動ログから健康状態の変化を予測するモデルの開発を担当しています。",
              "ウェアラブルデバイスから取得されるバイタルデータのクレンジングと特徴量抽出を行っています。",
              "医師の知見をアルゴリズム化し、パーソナライズされた健康アドバイスの生成ロジックを構築しています。",
              "ABテストの設計と分析を行い、プロダクトの機能改善に向けた意思決定を支援しています。",
              "データの整合性を担保するためのデータパイプラインの構築と運用を担っています。",
              "社内のデータ活用基盤の整備と、セキュリティ基準に則ったデータアクセス制御の設計を行っています。"
            ],
            "q_message_to_applicants": [
              "データの力で医療の常識を塗り替えたい方、ぜひ一緒に挑戦しましょう。",
              "複雑な課題をシンプルに解き明かすのが好きな方には最高の環境です。",
              "あなたの分析が、誰かの未来の健康を作る第一歩になります。",
              "プロフェッショナルな仲間と共に、妥協のない仕事を追求しませんか。",
              "HealthTechの最前線で、データサイエンスの真価を発揮したい方を待っています。",
              "まずはカジュアルに、私たちの描く未来についてお話しさせてください。"
            ]
          }
        },
        {
          "area": "development",
          "title": null,
          "count": 12,
          "answers": {
            "q_why_joined": [
              "RailsとGraphQLを用いたモダンな開発環境で、社会貢献性の高い開発をしたいと考えました。",
              "Vue.jsによるリッチなフロントエンド開発に携わりたかったからです。",
              "医療というミッションクリティカルな領域での、堅牢なシステム設計に興味がありました。",
              "フルフレックスで、自身の生活リズムを尊重しながらプロフェッショナルな仕事ができるからです。",
              "選考でのコードレビューが非常に丁寧で、技術を大切にする文化を確信しました。",
              "エンジニアも企画段階から参加し、ビジネスサイドと対等に話せる体制に惹かれました。",
              "Docker/AWSを用いたクラウドネイティブなインフラ構築に挑戦したかったからです。",
              "前職でのシステム開発経験を、HealthTechという成長市場で活かしたいと思いました。",
              "少数精鋭のチームで、一人ひとりの裁量が大きく、スピード感のある開発ができるからです。",
              "技術的負債への理解があり、継続的なリファクタリングにリソースを割いている点です。",
              "医師やデータサイエンティストといった専門家と、チームでプロダクトを作る経験を求めていました。",
              "セキュリティとパフォーマンスに対して、高い基準を設けている点に技術的好奇心を刺激されました。"
            ],
            "q_what_attracted": [
              "GraphQLを採用しており、フロントエンドとバックエンドの連携が非常にスムーズな点です。",
              "コードの品質に対する意識が高く、CI/CDの整備も行き届いています。",
              "開発した機能がユーザーの健康改善にどう寄与したか、定量的・定性的に共有される文化です。",
              "ドキュメント文化が浸透しており、情報の透明性が非常に高いところです。",
              "ペアプログラミングやコードレビューを通じて、日常的にスキル向上を図れる点です。",
              "無駄な会議が少なく、エンジニアが集中して実装に取り組める時間が確保されています。",
              "AWSの最新サービスを積極的に検証し、プロダクトに導入する柔軟性があります。",
              "職種を問わず、合理的な提案であればすぐに採用されるスピード感です。",
              "複雑なデータドメインを、Railsのモデル設計でいかに綺麗に表現するかを追求できる点です。",
              "パフォーマンス改善用のスプリントが設けられており、技術的なこだわりを追求できる環境です。",
              "ユーザーインタビューの結果が共有され、エンジニアも課題を解像度高く理解できる点です。",
              "Slackでのやり取りが非常に理知的で、感情的な摩擦がほとんどないプロフェッショナルな組織です。"
            ],
            "q_team_atmosphere": [
              "フラットで、役職に関わらず意見を出し合える心理的安全性の高いチームです。",
              "失敗を責めるのではなく、仕組みでどう防ぐかを議論するポジティブな文化です。",
              "技術的な好奇心が旺盛なメンバーが多く、常に新しい情報の交換が行われています。",
              "各自が自律して動いており、マイクロマネジメントとは無縁の環境です。",
              "困ったときにはSlackですぐに誰かが助けてくれる、協力的な雰囲気です。",
              "夕会での進捗共有が簡潔で、各自の時間を尊重する文化が根付いています。",
              "デザインシステムが整備されており、エンジニアとデザイナーのコミュニケーションが円滑です。",
              "リリース前などは緊張感もありますが、基本的には穏やかで理知的な雰囲気です。",
              "自己研鑽を奨励しており、書籍購入やセミナー参加のサポートも充実しています。",
              "中途入社でも馴染みやすいよう、オンボーディング資料が非常に丁寧に作成されています。",
              "仕事とプライベートの切り分けがはっきりしており、メリハリのある働き方ができます。",
              "全社的に『さん』付けで呼び合い、互いへのリスペクトを欠かさないチームです。"
            ],
            "q_job_description": [
              "Ruby on Railsを用いたバックエンドのAPI開発とDB設計を担当しています。",
              "Vue.jsを用いた、ユーザーフレンドリーなダッシュボードの実装を行っています。",
              "GraphQLのスキーマ設計と、効率的なデータ取得のためのパフォーマンス最適化を担っています。",
              "AWSインフラのTerraformによるコード管理と、CI/CDパイプラインの構築を行っています。",
              "セキュリティ要件を満たすための、認証・認可基盤の構築と監査対応を担当しています。",
              "ウェアラブルデバイス連携のための、サードパーティAPIとの統合ロジックを実装しています。",
              "バックエンドの技術的負債の解消と、モジュール性の高いアーキテクチャへの刷新を主導しています。",
              "プロダクトの新機能開発において、要件定義から実装、テストまで一貫して携わっています。",
              "フロントエンドの共通コンポーネント作成と、デザインシステムの運用を行っています。",
              "バッチ処理の高速化や、大量の健康データの集計ロジックの改善を行っています。",
              "QAチームと連携し、自動テストの拡充とリリースクオリティの担保を担当しています。",
              "技術顧問との定例会議を通じて、技術選定やアーキテクチャの高度化を推進しています。"
            ],
            "q_message_to_applicants": [
              "技術で誰かの人生を豊かにしたいという想いを持つ方、ぜひ一緒に作りましょう。",
              "複雑な医療ドメインをエンジニアリングで解きほぐす楽しさが、ここにはあります。",
              "成長途中の組織で、技術とプロダクトの両面で影響力を発揮したい方を歓迎します。",
              "最高水準のセキュリティと品質を追求する環境で、腕を磨きませんか。",
              "まずはカジュアルに、私たちのコードや開発スタイルについてお話ししましょう。",
              "ユーザーファーストな開発を通じて、社会に大きなインパクトを届けましょう。",
              "フラットでプロフェッショナルな仲間たちが、あなたのジョインを待っています。",
              "HealthTechという難易度の高い領域に、一緒に立ち向かえる仲間を探しています。",
              "自分の書いたコードが、誰かの健康を守る。その実感を共に分かち合いましょう。",
              "学び続ける姿勢を大切にする文化の中で、共に成長していきませんか。",
              "エンジニアリングの楽しさを最大限に享受できる環境が整っています。",
              "あなたのプロフェッショナリズムを、VitalCareで最大限に発揮してください。"
            ]
          }
        },
        {
          "area": "operations",
          "title": null,
          "count": 6,
          "answers": {
            "q_why_joined": [
              "医療サービスの円滑な運営を支える仕組み作りに興味を持ったからです。",
              "複雑なPHR活用フローを整理し、現場が使いやすいオペレーションを構築したいと考えました。",
              "医師やエンジニアの間に入り、事業を加速させる役割に魅力を感じたためです。",
              "スタートアップの成長をバックオフィスから支える経験を積みたかったからです。",
              "医療という重要領域で、ミスが許されない緊張感のある仕事に挑戦したいと思いました。",
              "ミッションへの強い共感と、組織としての誠実な姿勢に惹かれたからです。"
            ],
            "q_what_attracted": [
              "属人的な業務を排除し、徹底的に仕組み化・自動化を推進する文化です。",
              "現場の課題がすぐに改善要望としてプロダクトに反映される、風通しの良さです。",
              "Slack一つで全部署と連携でき、意思決定のスピードが非常に速い点です。",
              "業務の効率化が、直接ユーザーへの価値提供につながっていると実感できる点です。",
              "フルリモートでも業務プロセスが可視化されており、働きやすさが担保されている点です。",
              "新しいツールや手法を積極的に取り入れる、変化を恐れない柔軟な姿勢です。"
            ],
            "q_team_atmosphere": [
              "几帳面で誠実なメンバーが多く、非常に信頼感のあるチームです。",
              "常に改善の余地を探しており、前例にとらわれない思考が尊重されます。",
              "お互いの業務負担を気遣い、フォローし合う体制が自然とできています。",
              "定期的な1on1があり、個人のキャリア形成にも真剣に向き合ってくれます。",
              "議論は活発ですが、最終的な納得感と一貫性を大切にする雰囲気です。",
              "目標達成に対する意識が高く、チームで一丸となって取り組む熱量があります。"
            ],
            "q_job_description": [
              "導入先医療機関との契約管理や、アカウント発行のフロー構築を担当しています。",
              "ユーザーから寄せられる要望を整理し、開発優先順位の基礎資料を作成しています。",
              "個人情報保護に関するガイドラインの運用と、社内研修の企画・実施を行っています。",
              "提携パートナー企業との連携業務や、共同プロジェクトの進行管理を担っています。",
              "社内のDX推進として、SaaSツールの導入・統合による業務効率化をリードしています。",
              "プロダクトのリリースに伴うマニュアル整備や、オペレーションの検証を担当しています。"
            ],
            "q_message_to_applicants": [
              "組織の屋台骨として、これからの医療インフラを共に支えていきましょう。",
              "変化の多い環境を楽しみながら、仕組みをゼロから作りたい方を待っています。",
              "あなたの細やかな配慮と実行力が、サービスの信頼を形作ります。",
              "プロフェッショナルな仲間と共に、最高水準のオペレーションを目指しませんか。",
              "理知的で誠実なチームで、やりがいのある仕事に挑戦しましょう。",
              "まずはカジュアルに、私たちの組織課題についてお話しさせてください。"
            ]
          }
        },
        {
          "area": "customer",
          "title": null,
          "count": 5,
          "answers": {
            "q_why_joined": [
              "導入して終わりではなく、ユーザーの健康改善まで伴走できるCSの役割に惹かれました。",
              "医療従事者としての経験を活かし、ITの力でより多くの人を救いたいと考えたからです。",
              "顧客満足度を第一に考える、プロダクトの誠実なスタンスに共感したためです。",
              "データに基づいて顧客へのアドバイスができる、論理的なCS体制を求めていました。",
              "ミッション実現に向けて、ユーザーの声を直接プロダクトに届けたいと思ったからです。"
            ],
            "q_what_attracted": [
              "顧客からの『ありがとう』の声が全社Slackで共有され、称賛される文化です。",
              "チャーンレートが低く、真に顧客に愛されているプロダクトであることを実感できる点です。",
              "単なる操作説明ではなく、健康経営や予防医療のコンサルティングができる点です。",
              "エンジニアとの距離が近く、バグ修正や機能要望への対応が驚くほど速いことです。",
              "ユーザーコミュニティの運営など、既存のCSの枠を超えた挑戦ができる環境です。"
            ],
            "q_team_atmosphere": [
              "ユーザーへの深い共感力を持ちながら、プロ意識の高いメンバーが揃っています。",
              "ナレッジの共有が非常に盛んで、個人の成功をチームの財産にする文化です。",
              "心理的安全性が高く、難しい事案もチーム全体で知恵を出し合って解決します。",
              "オンとオフの切り替えがはっきりしており、メリハリを持って働ける雰囲気です。",
              "常に『ユーザーのためになるか』を問い直し、本質的な改善を目指すチームです。"
            ],
            "q_job_description": [
              "法人顧客へのオンボーディング支援と、継続的な活用状況の分析・提案を行っています。",
              "ユーザーからの問い合わせ対応と、そこから得られた課題の構造化・フィードバックを担当しています。",
              "ヘルプセンターのコンテンツ作成や、活用セミナーの企画・登壇を行っています。",
              "ヘルスケアデータの活用方法に関する、クライアント向けの教育プログラムを構築しています。",
              "解約防止策の立案や、アップセル・クロスセルに向けたマーケティングチームとの連携を担っています。"
            ],
            "q_message_to_applicants": [
              "顧客の成功を自分のことのように喜べる方、ぜひ一緒に働きましょう。",
              "あなたのホスピタリティと分析力で、予防医療を当たり前の文化にしませんか。",
              "ユーザーに寄り添い、共に成長できる環境がここにあります。",
              "プロフェッショナルなCS組織を一緒に作り上げていく仲間を募集中です。",
              "まずはあなたの顧客体験に対する想いを聞かせてください。"
            ]
          }
        },
        {
          "area": "sales",
          "title": null,
          "count": 5,
          "answers": {
            "q_why_joined": [
              "社会的意義の大きいプロダクトを、自信を持って広めたいと考えたからです。",
              "医師とデータサイエンティストが作る圧倒的な信頼性が、営業としての武器になると確信しました。",
              "従来の『売るだけ』の営業ではなく、市場を創る立ち上げフェーズに興味がありました。",
              "成果が正当に評価され、かつ組織全体の成長に貢献できる環境だと思ったからです。",
              "代表の熱いビジョンと、地に足の着いたビジネスモデルのバランスに惹かれました。"
            ],
            "q_what_attracted": [
              "顧客の課題を解決するための提案資料やスクリプトが日々進化する、アジャイルな体制です。",
              "インサイドセールスからのトスアップが質・量ともに高く、商談に集中できる点です。",
              "他部署との壁がなく、開発チームに直接顧客のニーズを伝えられる環境です。",
              "押し売りではなく、顧客の健康課題に深く入り込むソリューション営業ができる点です。",
              "医療機関や大手企業の上層部と対等に議論し、信頼を築いていくプロセスの面白さです。"
            ],
            "q_team_atmosphere": [
              "個人の目標達成はもちろん、チームでのナレッジ共有を非常に大切にする文化です。",
              "ポジティブで活力がありますが、根拠のない精神論ではなく論理を重んじる雰囲気です。",
              "失敗をオープンにし、そこから全員で学ぶ姿勢が根付いています。",
              "営業同士の仲が良く、商談後の振り返りやロールプレイングも頻繁に行われています。",
              "役職に関係なく、プロセス改善のための提案が歓迎されるフラットな環境です。"
            ],
            "q_job_description": [
              "中堅・大手企業の人事部門への、健康経営プラットフォームの導入提案を担当しています。",
              "医療機関向けのPHR利活用支援ソリューションの、新規開拓からクロージングまでを担っています。",
              "インサイドセールスチームと連携し、ターゲット選定とアプローチ戦略の策定を行っています。",
              "ウェビナーや展示会での登壇、およびリード獲得後のナーチャリング施策の実行を担当しています。",
              "既存顧客へのリレーション構築を通じて、プロダクトの追加導入やアップセルを提案しています。"
            ],
            "q_message_to_applicants": [
              "あなたの営業力で、日本の健康の未来をアップデートしませんか。",
              "本質的な価値があるプロダクトを広める喜びを、共に味わいましょう。",
              "主体的に動き、自ら市場を切り拓きたい方には最高のフィールドです。",
              "プロフェッショナルな営業チームの一員として、切磋琢磨できる方をお待ちしています。",
              "私たちと一緒に、HealthTechのトップランナーを目指しましょう。"
            ]
          }
        },
        {
          "area": "corporate",
          "title": null,
          "count": 3,
          "answers": {
            "q_why_joined": [
              "医療スタートアップという、ガバナンスが極めて重要な組織の基盤作りに挑戦したかったからです。",
              "「健康を資産に変える」というミッションを、内部から支える役割に誇りを感じたためです。",
              "成長企業のダイナミズムを、バックオフィスからコントロールする面白さに惹かれました。"
            ],
            "q_what_attracted": [
              "フルリモート・フルフレックスといった多様な働き方を、自ら体現し改善できる柔軟性です。",
              "コーポレート部門もDXを推進しており、徹底した効率化を追求する姿勢に共感しました。",
              "情報セキュリティや法令遵守に対し、全社員が高い意識を持っているため、専門性を発揮しやすい点です。"
            ],
            "q_team_atmosphere": [
              "誠実でプロ意識が高く、細かな部分まで配慮が行き届くメンバーが揃っています。",
              "互いの専門領域（労務、財務、法務等）を尊重し、横断的に連携する協力的なチームです。",
              "現状に満足せず、常により良い仕組みを模索し続ける、前向きで理知的な雰囲気です。"
            ],
            "q_job_description": [
              "採用事務、労務、経理の基盤構築と、月次の決算業務のリードを担当しています。",
              "ISMSの維持管理や、医療系ガイドラインに準拠した社内規定の整備・運用を担っています。",
              "全社の予算管理とKPIの可視化、および取締役会の運営サポートを行っています。"
            ],
            "q_message_to_applicants": [
              "攻めと守りのバランスを大切にし、組織を支えるプロフェッショナルを募集しています。",
              "社員が安心してミッションに集中できる環境を、共に作っていきませんか。",
              "変化を楽しみ、安定感を持って組織をリードしてくれる仲間を待っています。"
            ]
          }
        }
      ],
      "answers": {}
    },
    {
      "key": "nest_tech",
      "name": "株式会社Nest Tech",
      "industry": "PropTech",
      "size": "35",
      "company_profile": {
        "mission": "テクノロジーで住まいを最適化し、心地よい暮らしの基盤をアップデートする",
        "description": "不動産業界の不透明な商習慣をデジタルで変革するPropTechスタートアップ。煩雑なアナログ業務を徹底的に自動化し、住み手と貸し手の双方がよりスムーズで納得感のある意思決定を行えるプラットフォームを構築。",
        "strengths": [
          "現場の痛みを深く理解した上で、複雑な業務ドメインを解きほぐす高いモデリング能力",
          "一時的な利益よりもプロダクトの継続性を重んじ、技術債務と向き合う誠実な開発文化",
          "部署間の垣根が低く、全社員が『ユーザー体験』を共通言語にする高いプロダクトオーナーシップ"
        ],
        "tone": "温かみがありながらも論理的。生活の基盤である『住まい』への敬意を持ち、日常に溶け込む洗練された使い勝手を追求する誠実なトーン。"
      },
      "tech_environment": {
        "tech_stack": "Ruby on Rails, Vue.js, GraphQL, AWS, Docker",
        "development_style": "複雑な不動産業務フローを整理しながら開発するため、ビジネスサイド（営業・CS）とエンジニアが密に連携して仕様を策定。定期的にパフォーマンス改善や技術的負債の解消にスプリントを割くなど、長期的に愛されるプロダクト作りを重視しています。"
      },
      "team_composition": [
        {
          "area": "management",
          "title": "ceo",
          "count": 1,
          "answers": {
            "q_founding_reason": [
              "前職の不動産取引で感じた不透明さや非効率なプロセスを、テクノロジーの力で解消し、誰もが安心して住まいを選べる世界を作りたいと思い創業しました。"
            ],
            "q_company_vision": [
              "『不動産流通のスタンダードを再定義する』ことです。データとシステムによって、業界に関わるすべての人がより付加価値の高い仕事に集中できるインフラを目指します。"
            ],
            "q_what_kind_of_people": [
              "業界の商習慣を否定するのではなく、リスペクトした上で『より良くするには？』を粘り強く考え、実行に移せる方と一緒に働きたいです。"
            ],
            "q_company_challenge": [
              "プロダクトの急成長に伴い、さらなるスピード感を持った新機能開発と、より強固な組織基盤の構築を同時に進めていくことが現在の大きな挑戦です。"
            ]
          }
        },
        {
          "area": "management",
          "title": "coo",
          "count": 1,
          "answers": {
            "q_company_vision": [
              "事業を再現性のある形でスケールさせ、Nest Techのサービスを不動産業界の『当たり前』のツールにすることを目指しています。"
            ],
            "q_what_kind_of_people": [
              "目標達成への強い執着心を持ちつつ、チーム全体の最適化を常に意識して動ける、柔軟性と芯の強さを併せ持った方です。"
            ],
            "q_company_challenge": [
              "マーケットの拡大に合わせて、営業・CS・オペレーションの各部門がさらに有機的に連携し、顧客体験を最大化できる体制への進化が必要です。"
            ]
          }
        },
        {
          "area": "management",
          "title": "cto",
          "count": 1,
          "answers": {
            "q_company_vision": [
              "技術的な複雑性を排除し、ユーザーにとって圧倒的に使いやすいプロダクトを提供し続けること。そして、エンジニアが技術探求と事業貢献を高いレベルで両立できる組織を作ることです。"
            ],
            "q_what_kind_of_people": [
              "複雑なドメイン知識をコードに落とし込むことを楽しめる方、また、ビジネスサイドのメンバーと技術的なトレードオフを建設的に議論できる方。"
            ],
            "q_company_challenge": [
              "膨大な不動産データをより高速かつ安全に扱うためのアーキテクチャへの刷新と、開発生産性を最大化させるためのエンジニアリング文化の醸成です。"
            ]
          }
        },
        {
          "area": "sales",
          "title": null,
          "count": 12,
          "answers": {
            "q_why_joined": [
              "不動産業界の負を本気で解決しようとするプロダクトの力に惹かれました。",
              "前職の仲介経験を活かし、より広い視点で業界を変革したいと思ったからです。",
              "急成長中のスタートアップで、自身の営業力を試したいと考えたため。",
              "代表の掲げるビジョンに深く共感し、このチームの一員になりたいと強く感じました。",
              "IT化が遅れている領域で、真に顧客に貢献できるソリューションだと確信したからです。",
              "実力主義でありながら、チームで助け合う文化があることに魅力を感じました。",
              "「売って終わり」ではなく、プロダクトと共に成長できる環境を求めていました。",
              "PropTechの市場可能性と、Nest Techの独自性に将来性を感じたため。",
              "面談でお会いした方々のプロ意識の高さと、誠実な人柄に惹かれました。",
              "アナログな営業スタイルを脱却し、データに基づいた戦略的な営業を経験したかったため。",
              "裁量権が大きく、自ら提案して施策を動かせる環境だと感じたからです。",
              "社会的意義が大きく、自信を持って提案できるプロダクトを扱いたかったため。"
            ],
            "q_what_attracted": [
              "現場の声を即座にプロダクトへ反映してくれる開発チームとの距離の近さです。",
              "インサイドセールスからのパスが非常に質が高く、効率的に商談に集中できる点です。",
              "成功事例の共有が活発で、チーム全体でスキルアップしていける環境に惹かれました。",
              "顧客に深く入り込み、業務改善のコンサルティングまで踏み込める点です。",
              "KPIが明確で、自分の頑張りが数字として可視化されるスピード感が心地よいです。",
              "営業資料やツールが常にアップデートされ、クリエイティブな提案ができる点です。",
              "役職に関係なく、良いアイデアは即採用されるフラットな社風に驚きました。",
              "多様なキャリアパスがあり、セールスから企画やマネジメントも目指せる点。",
              "不動産業界のプロフェッショナルとして、深い知識が身につく環境です。",
              "フルフレックス制度を活用し、商談スケジュールを自ら最適化できる柔軟性。",
              "Slackでの称賛文化があり、成約時には部署を越えてお祝いしてくれる点です。",
              "最新のSaaSツールを駆使した、無駄のないスマートな営業フロー。"
            ],
            "q_team_atmosphere": [
              "非常に活気があり、ポジティブなエネルギーに満ちたチームです。",
              "困ったときは即座にアドバイスがもらえる、心理的安全性の高い雰囲気です。",
              "個人の目標はありますが、達成のためにチーム一丸となる連帯感があります。",
              "オンとオフの切り替えがはっきりしており、集中して仕事に取り組める環境です。",
              "多様なバックグラウンドを持つメンバーが、互いの強みを尊重し合っています。",
              "定期的な振り返りがあり、失敗を次の成功への学びとして捉える文化です。",
              "役員との距離も近く、経営の考えを直接聞く機会が多いオープンな組織です。",
              "若手からベテランまで、全員が主体性を持って動く自律した集団です。",
              "ユーモアがあり、Slackでのコミュニケーションも非常にスムーズです。",
              "ランチや雑談チャンネルなど、リモート下でも交流が盛んです。",
              "新しいことへの挑戦を全力でバックアップしてくれる雰囲気があります。",
              "顧客第一主義が徹底されており、誠実に仕事に向き合える環境です。"
            ],
            "q_job_description": [
              "不動産仲介会社様への新規導入提案から、契約締結までを担当しています。",
              "大手不動産会社様向けの深耕営業と、全社導入に向けたプロジェクト管理。",
              "インサイドセールスとして、リードの獲得と商談設定の最適化を行っています。",
              "新規マーケット開拓のためのターゲット選定と、アプローチ手法の確立。",
              "ウェビナーの企画運営を通じた、見込み顧客へのナーチャリング。 ",
              "代理店様との連携を強化し、販売チャネルを拡大するパートナーセールス。",
              "商談でのデモンストレーションと、顧客の課題に合わせた活用提案。",
              "セールスイネーブルメントとして、営業チームの教育や型化を推進。",
              "顧客ニーズを収集し、プロダクトマネージャーへ機能改善案を提出。",
              "入社後のオンボーディング支援と、初期の活用定着までを伴走します。",
              "契約更新に向けたリレーション構築と、アップセル提案の実施。",
              "市場調査に基づいた新しい営業戦略の立案と実行。"
            ],
            "q_message_to_applicants": [
              "不動産業界を本気で変えたいという熱い志を持った方、お待ちしています！",
              "自身の成長と業界の変革を同時に実感できる、最高にエキサイティングな環境です。",
              "「考える営業」をしたい方にとって、これ以上のフィールドはありません。",
              "一緒にPropTechのトップランナーとして、新しい景色を見に行きませんか？",
              "あなたの経験が、レガシーな業界を変える大きな力になります。",
              "まずはカジュアルにお話ししましょう。私たちの挑戦を伝えさせてください！",
              "自ら課題を見つけ、主体的に動ける方には無限のチャンスがある会社です。",
              "チームで大きな目標を達成する喜びを、ぜひ一緒に味わいましょう。",
              "プロ意識の高い仲間たちと、切磋琢磨しながら成長していける環境です。",
              "不動産×Techの可能性は無限大です。一緒に未来のスタンダードを作りましょう。",
              "誠実に顧客と向き合い、価値を提供したい方を全力で歓迎します。",
              "これまでのキャリアを、急成長スタートアップでさらに輝かせませんか？"
            ]
          }
        },
        {
          "area": "operations",
          "title": null,
          "count": 6,
          "answers": {
            "q_why_joined": [
              "複雑な不動産実務を整えることで、組織のスピードを加速させたいと思ったからです。",
              "オペレーションの構築が、サービスの成功に直結するフェーズに魅力を感じました。",
              "前職での事務経験を活かし、よりIT寄りの環境でキャリアを築きたかったため。",
              "現場の『不』を取り除き、メンバーが本来の業務に集中できる環境を作りたいと考えました。",
              "事業の成長を縁の下から支える、重要かつ専門性の高い役割だと感じたからです。",
              "効率化を追求する文化があり、自身の改善提案が形になりやすい環境だと思ったため。"
            ],
            "q_what_attracted": [
              "「とりあえずやる」ではなく、仕組み化・自動化を最優先する合理的な考え方です。",
              "ビジネスサイドと開発サイドを繋ぐハブとして、広い視点で事業に関われる点。",
              "現場の細かな課題にも真摯に向き合い、改善を惜しまないチームの姿勢です。",
              "ノーコードツールなどを積極的に活用し、自らシステムを組める点に惹かれました。",
              "業務フローが整理されることで、顧客への価値提供が早まるのを実感できる喜び。",
              "変化の激しい環境で、常に新しい運用の形を模索していけるワクワク感。"
            ],
            "q_team_atmosphere": [
              "細部へのこだわりと、全体最適の視点を両立させたプロフェッショナルなチーム。",
              "どんな小さな疑問も放置せず、全員で解決策を話し合える風通しの良さがあります。",
              "ミスを責めるのではなく「仕組みのどこに欠陥があったか」を論理的に議論する文化です。",
              "穏やかで丁寧なメンバーが多く、非常に協力的な雰囲気の中で仕事ができます。",
              "改善提案が称賛される文化で、常に「もっと良くできる」という前向きな姿勢があります。",
              "個々の自律性が高く、各々が自分の持ち場で責任を持って完結させる信頼関係。"
            ],
            "q_job_description": [
              "不動産データの入稿・管理フローの構築と、品質管理の徹底。",
              "Salesforce等のSFA/CRMの設計・運用と、データ分析による営業支援。",
              "契約から導入までの事務プロセスの自動化と、マニュアルの整備。",
              "社内のDX推進として、各種SaaSツールの導入・連携設定の実施。",
              "外部パートナー様との連携窓口と、アウトソーシングの管理。",
              "全社の開発生産性を高めるための、社内ワークフローの改善・企画。"
            ],
            "q_message_to_applicants": [
              "仕組み作りを通じて、事業成長の基盤を一緒に強固にしていきましょう！",
              "「もっと効率化できるはず」という視点をお持ちの方、ぜひお力をお貸しください。",
              "変化を楽しむ心と、地道な改善を積み重ねる粘り強さを持った方を歓迎します。",
              "オペレーションの力で、スタートアップの爆発的な成長を支える経験は一生の財産になります。",
              "あなたの改善一つで、メンバー全員の数時間が生まれる。そんなやりがいのある仕事です。",
              "フラットな組織で、これまでの経験を活かした自分なりの正解を形にしませんか？"
            ]
          }
        },
        {
          "area": "development",
          "title": null,
          "count": 8,
          "answers": {
            "q_why_joined": [
              "Ruby on RailsとGraphQLを用いたモダンな技術スタックでの開発に興味がありました。",
              "複雑な不動産ドメインをどうコードで表現するかという技術的挑戦に惹かれました。",
              "ビジネスサイドとエンジニアが対等に議論する開発スタイルに共感したからです。",
              "自身の書いたコードが、アナログな業界の負を直接解決する実感が持てると思ったため。",
              "少数精鋭で、技術選定からアーキテクチャ設計まで深く関われる環境を求めていました。",
              "選考での技術面談が非常に本質的で、このチームなら成長できると確信しました。",
              "フルリモート・フルフレックスで、技術研鑽と生活を両立できる環境に惹かれたため。",
              "長期的なメンテナンス性を考慮した開発を重視する姿勢に魅力を感じました。"
            ],
            "q_what_attracted": [
              "ドメイン駆動設計などを取り入れ、複雑なビジネスロジックを整理していく文化です。",
              "スクラム開発が形骸化せず機能しており、常に優先順位が整理されている点。",
              "開発の初期段階からエンジニアが企画に参加し、仕様への提案が歓迎されるところ。",
              "技術的負債に対して、チーム全員で向き合い定期的にリファクタリングの時間を確保している点。",
              "フロントエンドからバックエンドまで、領域を限定せず幅広く挑戦できる柔軟性。",
              "コードレビューが丁寧で、より良い設計のための議論が活発に行われている点。",
              "ユーザーの反応を定量・定性の両面でキャッチアップし、開発に活かせる環境。",
              "技術顧問や経験豊富なシニアエンジニアから、質の高いフィードバックが得られる点。"
            ],
            "q_team_atmosphere": [
              "技術への探究心が強く、新しいライブラリや手法の導入にも積極的なチームです。",
              "心理的安全性が高く、失敗を共有し仕組みでカバーしようとする建設的な雰囲気。",
              "Slackでのやり取りも活発ですが、集中時間も尊重されるメリハリのある文化。",
              "ビジネスサイドとの壁がなく、疑問があればすぐにドメイン知識を聞きに行けるフラットさ。",
              "各自がプロフェッショナルとして自律しつつも、必要なときはペアプロなどで助け合う環境。",
              "週次の技術共有会があり、各自が学んだ知見を惜しみなくアウトプットする習慣。",
              "代表も含め、全員がプロダクトの価値を最大化することに真摯に向き合っています。",
              "静かに集中する時間と、ワイワイ議論する時間のバランスが良いチームです。"
            ],
            "q_job_description": [
              "RailsとGraphQLを用いた、不動産管理機能のバックエンド設計と実装。",
              "Vue.jsを用いた、複雑な入力フォームやダッシュボードのフロントエンド開発。",
              "不動産データの正規化と、大量データを扱うバッチ処理の最適化。",
              "Terraformを用いたAWSインフラのコード管理と、CI/CD環境の整備。",
              "新規事業におけるAPI設計と、外部サービスとのセキュアな連携実装。",
              "パフォーマンスチューニングや、SQLのクエリ最適化を通じたUX改善。",
              "QAチームと連携したテスト自動化の推進と、品質管理プロセスの構築。",
              "ビジネスサイドと連携した、ユーザー要求の定義と技術的な実現方法の検討。"
            ],
            "q_message_to_applicants": [
              "複雑な課題を技術でシンプルにする。そんな楽しさを一緒に味わいましょう！",
              "プロダクト志向のエンジニアにとって、ここは最高の挑戦の場です。",
              "技術力だけでなく、ビジネスを創る手応えを感じたい方、お待ちしています。",
              "レガシーな業界をコードでハックし、新しい価値を創造しましょう。",
              "あなたのエンジニアリングで、不動産業界の『当たり前』を書き換えませんか？",
              "モダンな技術スタックを使いこなし、質の高いプロダクトを一緒に育てましょう。",
              "まずはカジュアルに、私たちのアーキテクチャやコードについて語り合いましょう！",
              "自律したチームで、自分の影響力を最大限に発揮したい方を歓迎します。"
            ]
          }
        },
        {
          "area": "customer",
          "title": null,
          "count": 4,
          "answers": {
            "q_why_joined": [
              "導入がゴールではなく、その先の顧客の成功にコミットしたいと考えたからです。",
              "不動産業界のDXには、プロダクトの力だけでなくCSの伴走が不可欠だと感じたため。",
              "前職での人事や営業経験を活かし、顧客に深く寄り添う役割に挑戦したかったため。",
              "ユーザーの声が最もプロダクトに反映されやすい組織体制に魅力を感じました。"
            ],
            "q_what_attracted": [
              "チャーンレートが非常に低く、顧客から真に信頼されていることを実感できる点。",
              "単なる問い合わせ対応ではなく、経営課題に踏み込んだコンサルティングができること。",
              "CSチームのナレッジ共有が非常にスピーディーで、常に最新の成功事例を学べる点。",
              "ユーザーコミュニティの運営など、一対多のテックタッチな施策にも挑戦できる柔軟性。"
            ],
            "q_team_atmosphere": [
              "顧客の成功を全員で喜び、課題には全員で知恵を絞る、非常に温かくプロフェッショナルなチーム。",
              "誰かが作成した資料やTipsがすぐに共有され、チームの標準になるスピード感があります。",
              "他部署へのフィードバックも建設的に行われ、全社でユーザー体験を高める文化です。",
              "個人の目標とチームの目標が調和しており、お互いを自然にフォローし合える雰囲気です。"
            ],
            "q_job_description": [
              "新規導入企業様へのオンボーディングと、初期の活用目標の設定・支援。",
              "定期的な活用状況の分析に基づく、改善提案とQBR（四半期定例会）の実施。",
              "ヘルプセンターのコンテンツ拡充や、ユーザー向けの機能アップデート案内。",
              "顧客要望を構造化して開発チームへフィードバックし、新機能の要件定義を支援。"
            ],
            "q_message_to_applicants": [
              "顧客の『ありがとう』を一番近くで聞ける、やりがいの大きなポジションです。",
              "CS組織の仕組み作りから関わりたい、主体性のある方を全力で歓迎します！",
              "不動産業界の未来を、顧客と一緒に作っていく喜びを分かち合いましょう。",
              "ユーザーの声でプロダクトを変えたい。そんな熱い思いを持った方、待っています。"
            ]
          }
        },
        {
          "area": "corporate",
          "title": null,
          "count": 2,
          "answers": {
            "q_why_joined": [
              "急成長するスタートアップを、守りと攻めの両面から支える基盤作りに挑戦したかった。",
              "Nest Techの掲げる誠実なビジョンに共感し、コーポレートから体現したいと思ったため。"
            ],
            "q_what_attracted": [
              "コーポレート部門もDXを推進し、いかに効率的で働きやすい環境を作るかに注力している点。",
              "フルリモート等の多様な働き方を自ら設計し、組織文化として定着させていける裁量の大きさ。"
            ],
            "q_team_atmosphere": [
              "誠実でホスピタリティが高く、細やかな配慮とロジカルさを兼ね備えたメンバーです。",
              "前例に縛られず、組織のフェーズに合わせて常に最適な形を模索し続ける柔軟なチーム。"
            ],
            "q_job_description": [
              "採用広報から労務、経理、法務チェックまで、バックオフィス業務全般の構築と運用。",
              "ISMS取得や内部統制の整備、社内イベントを通じた組織エンゲージメントの向上施策。"
            ],
            "q_message_to_applicants": [
              "社員全員が迷いなく走れる、最高の舞台を一緒に整えていきませんか？",
              "変化の多い環境を楽しみ、土台作りを面白がれる方をお待ちしています！"
            ]
          }
        }
      ],
      "answers": {}
    }
  ]
}
